Workbook
Name Slicer_Order_Date: #N/A
Name Slicer_Payment_Method: #N/A
Name Slicer_Quantity: #N/A
Name Slicer_Status: #N/A
Name Total_Revenue: Table1[[#Headers],[Total ]]

Sheet Pivot Tables
C2: Broducts Revenue | M2: Top Selling Category
C3: Broduct | D3: Sum of Total | E3: KPIS | F3: ="Top Selling Product = "&INDEX(C3:C8,MATCH(MAX(D3:D8),D3:D8,0)) -> Top Selling Product = shoes | M3: Category | N3: Sum of Quantity | O3: Sum of Total
C4: Comics | D4: 6629.68 | M4: Books | N4: 74 | O4: 13156.47 | P4: KPIS | Q4: ="Top Selling Category = "&INDEX(M4:M8,MATCH(MAX(O4:O8),O4:O8,0)) -> Top Selling Category = Clothings
C5: Basketball | D5: 6666.48 | M5: Clothings | N5: 57 | O5: 32475.08
C6: Jeans | D6: 6674.67 | M6: Electronics | N6: 25 | O6: 4587.15
C7: Lamp | D7: 8069.73 | M7: Home | N7: 69 | O7: 21416.28
C8: shoes | D8: 18219 | M8: Sports | N8: 52 | O8: 16130.89
M11: Orders By Bayment Method
M12: Bayment Method | N12: Count of Order_ID | O12: KPIS | P12: ="Most Used Payment Method = "&INDEX(M13:M16,MATCH(MAX(N13:N16),N13:N16,0)) -> Most Used Payment Method = Cash on Delivery
C13: Sum of Total | D13: Count of Order_ID | E13: Sum of Quantity | F13: KPIS | G13: ="AOV = "&ROUND(GETPIVOTDATA("Sum of Total ",$C$13)/GETPIVOTDATA("Count of Order_ID",$C$13),2) -> AOV = 964.46 | M13: Bank Transfer | N13: 20
A14: Bayment Method By Revenue | C14: 87765.87 | D14: 91 | E14: 277 | M14: Cash on Delivery | N14: 30
A15: Bayment Method | B15: Sum of Total | M15: Credit Card | N15: 21
A16: Cash on Delivery | B16: 20640.58 | C16: KPIS | D16: ="Top Revenue by Bayment Method = "&INDEX(A16:A19,MATCH(MAX(B16:B19),B16:B19,0)) -> Top Revenue by Bayment Method = Bank Transfer | M16: PayPal | N16: 20
A17: Credit Card | B17: 20877.39
A18: PayPal | B18: 23122.74 | J18: Sales Date | M18: Product Quantity
A19: Bank Transfer | B19: 23125.16 | J19: Date | K19: Sum of Total | M19: Product | N19: Sum of Quantity | O19: KPIS | P19: ="Highiest Quantity Product = "&INDEX(M20:M24,MATCH(MAX(N20:N24),N20:N24,)) -> Highiest Quantity Product = shoes
J20: 2023 | K20: 1532.04 | M20: shoes | N20: 28
A21: Orders Status | J21: Jan | K21: 1532.04 | M21: Science | N21: 24
A22: Status | B22: Count of Order_ID | J22: May | K22: 0 | M22: Blender | N22: 23
A23: Cancelled | B23: 0.15384615 | J23: 2024 | K23: 15011.61 | M23: Lamp | N23: 23
A24: Delivered | B24: 0.10989011 | J24: Nov | K24: 7820.32 | M24: Comics | N24: 20
A25: Processing | B25: 0.24175824 | J25: Dec | K25: 7191.29
A26: Returned | B26: 0.26373626 | J26: 2025 | K26: 71222.22
A27: Shipped | B27: 0.23076923 | J27: Jan | K27: 7090.35
A28: Grand Total | B28: 1 | J28: Feb | K28: 9401.57
J29: Mar | K29: 5470.36
J30: Apr | K30: 1200.28
A31: Revenue By Orders Status | J31: May | K31: 5579.26
A32: Status | B32: Sum of Total | J32: Jun | K32: 4700.23
A33: Cancelled | B33: 0 | J33: Jul | K33: 10538.27
A34: Delivered | B34: 0.18161376 | J34: Aug | K34: 3335.06
A35: Processing | B35: 0.35873854 | J35: Sep | K35: 2606.01
A36: Returned | B36: 0 | J36: Oct | K36: 20200.43
A37: Shipped | B37: 0.4596477 | J37: Nov | K37: 1100.4
D41: Count of Order_ID | E41: Count of Customer_Name
D42: 91 | E42: 91

Sheet Dashboard

Sheet Pivot 2
A1: Status | B1: Returned
A3: Orders | B3: Sum of Total
A4: Electronics | B4: 0
A5: Books | B5: 0
A6: Home | B6: 0
A7: Clothings | B7: 0
A8: Sports | B8: 0
A9: Grand Total | B9: 0

Sheet Pivot 3
A1: Status | B1: (All)
A3: Orders | B3: Sum of Total
A4: Electronics | B4: 4587.15
A5: Books | B5: 13156.47
A6: Sports | B6: 16130.89
A7: Home | B7: 21416.28
A8: Clothings | B8: 32475.08
A9: Grand Total | B9: 87765.87

Sheet Pivot 4
A1: Status | B1: (All)
A3: Orders | B3: Sum of Total
A4: Books | B4: 13156.47
A5: Clothings | B5: 32475.08
A6: Electronics | B6: 4587.15
A7: Home | B7: 21416.28
A8: Sports | B8: 16130.89
A9: Grand Total | B9: 87765.87

Sheet Pivot 5
A1: Status | B1: (All)
A3: Orders | B3: Sum of Total
A4: Books | B4: 13156.47
A5: Clothings | B5: 32475.08
A6: Electronics | B6: 4587.15
A7: Home | B7: 21416.28
A8: Sports | B8: 16130.89
A9: Grand Total | B9: 87765.87

Sheet Pivot 6
A1: Status | B1: (All)
A3: Orders | B3: Sum of Total
A4: Books | B4: 13156.47
A5: Clothings | B5: 32475.08
A6: Electronics | B6: 4587.15
A7: Home | B7: 21416.28
A8: Sports | B8: 16130.89
A9: Grand Total | B9: 87765.87

Sheet E-Commerce sales
A1: ID | B1: Customer_Name | C1: Order_ID | D1: Order_Date | E1: Product | F1: Category | G1: Quantity | H1: Quality Check | I1: Quantity_Check2 | J1: Price | K1: Price Check 1 | L1: Price Check 2 | M1: Payment_Method | N1: Status | O1: Total | P1: Total_Check
A2: 155 | B2: Customer_155 | C2: ORD-20182 | D2: 45778 | E2: shoes | F2: =VLOOKUP(E2,Mapping!$A$1:$B$20,2,FALSE) -> Clothings | G2: 1 | H2: =IF(AND(G2<0,G2<>$N$4),"ERORR","OK") -> OK | I2: =ISNUMBER(G2) -> TRUE | J2: 523 | K2: =IF(OR(Table1[[#This Row],[Price]]>$S$20,Table1[[#This Row],[Price]]<$T$19),"Outlier","OK") -> OK | L2: =ISNUMBER(J2) -> TRUE | M2: PayPal | N2: Returned | O2: 0 | P2: =IF(AND(O2<0,O2<>N17),"ERORR","OK") -> OK
A3: 177 | B3: Customer_177 | C3: ORD-64136 | D3: 45866 | E3: Laptop | F3: =VLOOKUP(E3,Mapping!$A$1:$B$20,2,FALSE) -> Electronics | G3: 1 | H3: =IF(AND(G3<0,G3<>$N$4),"ERORR","OK") -> OK | I3: =ISNUMBER(G3) -> TRUE | J3: =MEDIAN(J26:J79) -> 569.19 | K3: =IF(OR(Table1[[#This Row],[Price]]>$S$20,Table1[[#This Row],[Price]]<$T$19),"Outlier","OK") -> OK | L3: =ISNUMBER(J3) -> TRUE | M3: Bank Transfer | N3: Returned | O3: 0 | P3: =IF(AND(O3<0,O3<>N18),"ERORR","OK") -> OK
A4: 175 | B4: Customer_175 | C4: ORD-56651 | D4: 45712 | E4: Headphones | F4: =VLOOKUP(E4,Mapping!$A$1:$B$20,2,FALSE) -> Electronics | G4: 1 | H4: =IF(AND(G4<0,G4<>$N$4),"ERORR","OK") -> OK | I4: =ISNUMBER(G4) -> TRUE | J4: 111.36 | K4: =IF(OR(Table1[[#This Row],[Price]]>$S$20,Table1[[#This Row],[Price]]<$T$19),"Outlier","OK") -> OK | L4: =ISNUMBER(J4) -> TRUE | M4: Credit Card | N4: Processing | O4: =Table1[[#This Row],[Price]]*Table1[[#This Row],[Quantity]] -> 111.36 | P4: =IF(AND(O4<0,O4<>N19),"ERORR","OK") -> OK
A5: 100 | B5: Customer_100 | C5: ORD-41285 | D5: 45618 | E5: Blender | F5: =VLOOKUP(E5,Mapping!$A$1:$B$20,2,FALSE) -> Home | G5: 3 | H5: =IF(AND(G5<0,G5<>$N$4),"ERORR","OK") -> OK | I5: =ISNUMBER(G5) -> TRUE | J5: 438 | K5: =IF(OR(Table1[[#This Row],[Price]]>$S$20,Table1[[#This Row],[Price]]<$T$19),"Outlier","OK") -> OK | L5: =ISNUMBER(J5) -> TRUE | M5: Cash on Delivery | N5: Shipped | O5: =Table1[[#This Row],[Price]]*Table1[[#This Row],[Quantity]] -> 1314 | P5: =IF(AND(O5<0,O5<>N20),"ERORR","OK") -> OK
A6: 197 | B6: Customer_197 | C6: ORD-79139 | D6: 45831 | E6: Blender | F6: =VLOOKUP(E6,Mapping!$A$1:$B$20,2,FALSE) -> Home | G6: 1 | H6: =IF(AND(G6<0,G6<>$N$4),"ERORR","OK") -> OK | I6: =ISNUMBER(G6) -> TRUE | J6: 545 | K6: =IF(OR(Table1[[#This Row],[Price]]>$S$20,Table1[[#This Row],[Price]]<$T$19),"Outlier","OK") -> OK | L6: =ISNUMBER(J6) -> TRUE | M6: PayPal | N6: Cancelled | O6: 0 | P6: =IF(AND(O6<0,O6<>N22),"ERORR","OK") -> OK | S6: ="Total Revenue = "&SUM(Table1[[Total ]]) -> Total Revenue = 82032.115
A7: 150 | B7: Customer_150 | C7: ORD-76902 | D7: 45623 | E7: Yoga Mat | F7: =VLOOKUP(E7,Mapping!$A$1:$B$20,2,FALSE) -> Sports | G7: 1 | H7: =IF(AND(G7<0,G7<>$N$4),"ERORR","OK") -> OK | I7: =ISNUMBER(G7) -> TRUE | J7: 206.19 | K7: =IF(OR(Table1[[#This Row],[Price]]>$S$20,Table1[[#This Row],[Price]]<$T$19),"Outlier","OK") -> OK | L7: =ISNUMBER(J7) -> TRUE | M7: Credit Card | N7: Returned | O7: 0 | P7: =IF(AND(O7<0,O7<>N22),"ERORR","OK") -> OK | S7: ="Total Order = "&COUNTA(Table1[Order_ID]) -> Total Order = 88
A8: 181 | B8: Customer_181 | C8: ORD-54481 | D8: 45655 | E8: Smartphone | F8: =VLOOKUP(E8,Mapping!$A$1:$B$20,2,FALSE) -> Electronics | G8: 1 | H8: =IF(AND(G8<0,G8<>$N$4),"ERORR","OK") -> OK | I8: =ISNUMBER(G8) -> TRUE | J8: 266.48 | K8: =IF(OR(Table1[[#This Row],[Price]]>$S$20,Table1[[#This Row],[Price]]<$T$19),"Outlier","OK") -> OK | L8: =ISNUMBER(J8) -> TRUE | M8: Cash on Delivery | N8: Cancelled | O8: 0 | P8: =IF(AND(O8<0,O8<>N23),"ERORR","OK") -> OK | S8: ="(AOV) = "&SUM(O:O)/COUNTA(D:D) -> (AOV) = 921.709157303371
A9: 132 | B9: Customer_132 | C9: ORD-40186 | D9: 45749 | E9: Yoga Mat | F9: =VLOOKUP(E9,Mapping!$A$1:$B$20,2,FALSE) -> Sports | G9: 1 | H9: =IF(AND(G9<0,G9<>$N$4),"ERORR","OK") -> OK | I9: =ISNUMBER(G9) -> TRUE | J9: 266.7 | K9: =IF(OR(Table1[[#This Row],[Price]]>$S$20,Table1[[#This Row],[Price]]<$T$19),"Outlier","OK") -> OK | L9: =ISNUMBER(J9) -> TRUE | M9: PayPal | N9: Delivered | O9: =Table1[[#This Row],[Price]]*Table1[[#This Row],[Quantity]] -> 266.7 | P9: =IF(AND(O9<0,O9<>N25),"ERORR","OK") -> OK | S9: ="Total Quantity Sold = "&SUM(G:G) -> Total Quantity Sold = 269
A10: 168 | B10: Customer_168 | C10: ORD-53430 | D10: 45965 | E10: Biography | F10: =VLOOKUP(E10,Mapping!$A$1:$B$20,2,FALSE) -> Books | G10: 2 | H10: =IF(AND(G10<0,G10<>$N$4),"ERORR","OK") -> OK | I10: =ISNUMBER(G10) -> TRUE | J10: 141.49 | K10: =IF(OR(Table1[[#This Row],[Price]]>$S$20,Table1[[#This Row],[Price]]<$T$19),"Outlier","OK") -> OK | L10: =ISNUMBER(J10) -> TRUE | M10: PayPal | N10: Cancelled | O10: 0 | P10: =IF(AND(O10<0,O10<>N27),"ERORR","OK") -> OK | S10: ="Unique Costomers = "&COUNTA(Mapping!D:D) -> Unique Costomers = 93
A11: 137 | B11: Customer_137 | C11: ORD-91254 | D11: 45711 | E11: Vacuum | F11: =VLOOKUP(E11,Mapping!$A$1:$B$20,2,FALSE) -> Home | G11: 3 | H11: =IF(AND(G11<0,G11<>$N$4),"ERORR","OK") -> OK | I11: =ISNUMBER(G11) -> TRUE | J11: =MEDIAN(J46:J94) -> 649.005 | K11: =IF(OR(Table1[[#This Row],[Price]]>$S$20,Table1[[#This Row],[Price]]<$T$19),"Outlier","OK") -> OK | L11: =ISNUMBER(J11) -> TRUE | M11: Cash on Delivery | N11: Delivered | O11: =Table1[[#This Row],[Price]]*Table1[[#This Row],[Quantity]] -> 1947.015 | P11: =IF(AND(O11<0,O11<>N28),"ERORR","OK") -> OK
A12: 162 | B12: Customer_162 | C12: ORD-27743 | D12: 45796 | E12: Blender | F12: =VLOOKUP(E12,Mapping!$A$1:$B$20,2,FALSE) -> Home | G12: 2 | H12: =IF(AND(G12<0,G12<>$N$4),"ERORR","OK") -> OK | I12: =ISNUMBER(G12) -> TRUE | J12: 553 | K12: =IF(OR(Table1[[#This Row],[Price]]>$S$20,Table1[[#This Row],[Price]]<$T$19),"Outlier","OK") -> OK | L12: =ISNUMBER(J12) -> TRUE | M12: Credit Card | N12: Returned | O12: 0 | P12: =IF(AND(O12<0,O12<>N28),"ERORR","OK") -> OK
A13: 186 | B13: Customer_186 | C13: ORD-90569 | D13: 45936 | E13: Laptop | F13: =VLOOKUP(E13,Mapping!$A$1:$B$20,2,FALSE) -> Electronics | G13: 1 | H13: =IF(AND(G13<0,G13<>$N$4),"ERORR","OK") -> OK | I13: =ISNUMBER(G13) -> TRUE | J13: 365.34 | K13: =IF(OR(Table1[[#This Row],[Price]]>$S$20,Table1[[#This Row],[Price]]<$T$19),"Outlier","OK") -> OK | L13: =ISNUMBER(J13) -> TRUE | M13: Bank Transfer | N13: Delivered | O13: =Table1[[#This Row],[Price]]*Table1[[#This Row],[Quantity]] -> 365.34 | P13: =IF(AND(O13<0,O13<>N30),"ERORR","OK") -> OK
A14: 105 | B14: Customer_105 | C14: ORD-22442 | D14: 45616 | E14: Tennis Racket | F14: =VLOOKUP(E14,Mapping!$A$1:$B$20,2,FALSE) -> Sports | G14: 3 | H14: =IF(AND(G14<0,G14<>$N$4),"ERORR","OK") -> OK | I14: =ISNUMBER(G14) -> TRUE | J14: =MEDIAN(J17:J69) -> 546.04 | K14: =IF(OR(Table1[[#This Row],[Price]]>$S$20,Table1[[#This Row],[Price]]<$T$19),"Outlier","OK") -> OK | L14: =ISNUMBER(J14) -> TRUE | M14: Cash on Delivery | N14: Cancelled | O14: 0 | P14: =IF(AND(O14<0,O14<>N29),"ERORR","OK") -> OK
A15: 102 | B15: Customer_102 | C15: ORD-84355 | D15: 45649 | E15: Tennis Racket | F15: =VLOOKUP(E15,Mapping!$A$1:$B$20,2,FALSE) -> Sports | G15: 1 | H15: =IF(AND(G15<0,G15<>$N$4),"ERORR","OK") -> OK | I15: =ISNUMBER(G15) -> TRUE | J15: 389.05 | K15: =IF(OR(Table1[[#This Row],[Price]]>$S$20,Table1[[#This Row],[Price]]<$T$19),"Outlier","OK") -> OK | L15: =ISNUMBER(J15) -> TRUE | M15: PayPal | N15: Delivered | O15: =Table1[[#This Row],[Price]]*Table1[[#This Row],[Quantity]] -> 389.05 | P15: =IF(AND(O15<0,O15<>N30),"ERORR","OK") -> OK
A16: 184 | B16: Customer_184 | C16: ORD-67799 | D16: 45703 | E16: Jeans | F16: =VLOOKUP(E16,Mapping!$A$1:$B$20,2,FALSE) -> Clothings | G16: 4 | H16: =IF(AND(G16<0,G16<>$N$4),"ERORR","OK") -> OK | I16: =ISNUMBER(G16) -> TRUE | J16: =MEDIAN(J82) -> 741.63 | K16: =IF(OR(Table1[[#This Row],[Price]]>$S$20,Table1[[#This Row],[Price]]<$T$19),"Outlier","OK") -> OK | L16: =ISNUMBER(J16) -> TRUE | M16: Bank Transfer | N16: Processing | O16: =Table1[[#This Row],[Price]]*Table1[[#This Row],[Quantity]] -> 2966.52 | P16: =IF(AND(O16<0,O16<>N33),"ERORR","OK") -> OK | R16: Q1 | S16: =_xlfn.QUARTILE.INC(J:J,1) -> 408.8575
A17: 113 | B17: Customer_113 | C17: ORD-23994 | D17: 45862 | E17: Fiction | F17: =VLOOKUP(E17,Mapping!$A$1:$B$20,2,FALSE) -> Books | G17: 1 | H17: =IF(AND(G17<0,G17<>$N$4),"ERORR","OK") -> OK | I17: =ISNUMBER(G17) -> TRUE | J17: 411.81 | K17: =IF(OR(Table1[[#This Row],[Price]]>$S$20,Table1[[#This Row],[Price]]<$T$19),"Outlier","OK") -> OK | L17: =ISNUMBER(J17) -> TRUE | M17: Credit Card | N17: Processing | O17: =Table1[[#This Row],[Price]]*Table1[[#This Row],[Quantity]] -> 411.81 | P17: =IF(AND(O17<0,O17<>N33),"ERORR","OK") -> OK | R17: q3 | S17: =_xlfn.QUARTILE.INC(J:J,3) -> 741.63
A18: 159 | B18: Customer_159 | C18: ORD-98162 | D18: 45866 | E18: Microwave | F18: =VLOOKUP(E18,Mapping!$A$1:$B$20,2,FALSE) -> Home | G18: 3 | H18: =IF(AND(G18<0,G18<>$N$4),"ERORR","OK") -> OK | I18: =ISNUMBER(G18) -> TRUE | J18: 163.16 | K18: =IF(OR(Table1[[#This Row],[Price]]>$S$20,Table1[[#This Row],[Price]]<$T$19),"Outlier","OK") -> OK | L18: =ISNUMBER(J18) -> TRUE | M18: PayPal | N18: Shipped | O18: =Table1[[#This Row],[Price]]*Table1[[#This Row],[Quantity]] -> 489.48 | P18: =IF(AND(O18<0,O18<>N34),"ERORR","OK") -> OK | R18: IQR | S18: =S17-S16 -> 332.7725
A19: 138 | B19: Customer_138 | C19: ORD-34319 | D19: 45878 | E19: Lamp | F19: =VLOOKUP(E19,Mapping!$A$1:$B$20,2,FALSE) -> Home | G19: 1 | H19: =IF(AND(G19<0,G19<>$N$4),"ERORR","OK") -> OK | I19: =ISNUMBER(G19) -> TRUE | J19: 531.06 | K19: =IF(OR(Table1[[#This Row],[Price]]>$S$20,Table1[[#This Row],[Price]]<$T$19),"Outlier","OK") -> OK | L19: =ISNUMBER(J19) -> TRUE | M19: PayPal | N19: Processing | O19: =Table1[[#This Row],[Price]]*Table1[[#This Row],[Quantity]] -> 531.06 | P19: =IF(AND(O19<0,O19<>N36),"ERORR","OK") -> OK | R19: Lower | S19: =S16-(1.5*S18) -> -90.30125 | T19: =ABS(S19) -> 90.30125
A20: 104 | B20: Customer_104 | C20: ORD-93614 | D20: 45950 | E20: Biography | F20: =VLOOKUP(E20,Mapping!$A$1:$B$20,2,FALSE) -> Books | G20: 1 | H20: =IF(AND(G20<0,G20<>$N$4),"ERORR","OK") -> OK | I20: =ISNUMBER(G20) -> TRUE | J20: 552.51 | K20: =IF(OR(Table1[[#This Row],[Price]]>$S$20,Table1[[#This Row],[Price]]<$T$19),"Outlier","OK") -> OK | L20: =ISNUMBER(J20) -> TRUE | M20: Cash on Delivery | N20: Processing | O20: =Table1[[#This Row],[Price]]*Table1[[#This Row],[Quantity]] -> 552.51 | P20: =IF(AND(O20<0,O20<>N37),"ERORR","OK") -> OK | R20: Upper | S20: =S17+1.5*S18 -> 1240.7887
A21: 169 | B21: Customer_169 | C21: ORD-75539 | D21: 45881 | E21: Basketball | F21: =VLOOKUP(E21,Mapping!$A$1:$B$20,2,FALSE) -> Sports | G21: 1 | H21: =IF(AND(G21<0,G21<>$N$4),"ERORR","OK") -> OK | I21: =ISNUMBER(G21) -> TRUE | J21: 582.13 | K21: =IF(OR(Table1[[#This Row],[Price]]>$S$20,Table1[[#This Row],[Price]]<$T$19),"Outlier","OK") -> OK | L21: =ISNUMBER(J21) -> TRUE | M21: Credit Card | N21: Returned | O21: 0 | P21: =IF(AND(O21<0,O21<>N38),"ERORR","OK") -> OK
A22: 108 | B22: Customer_108 | C22: ORD-64400 | D22: 45953 | E22: Science | F22: =VLOOKUP(E22,Mapping!$A$1:$B$20,2,FALSE) -> Books | G22: 1 | H22: =IF(AND(G22<0,G22<>$N$4),"ERORR","OK") -> OK | I22: =ISNUMBER(G22) -> TRUE | J22: 600.29 | K22: =IF(OR(Table1[[#This Row],[Price]]>$S$20,Table1[[#This Row],[Price]]<$T$19),"Outlier","OK") -> OK | L22: =ISNUMBER(J22) -> TRUE | M22: Cash on Delivery | N22: Processing | O22: =Table1[[#This Row],[Price]]*Table1[[#This Row],[Quantity]] -> 600.29 | P22: =IF(AND(O22<0,O22<>N39),"ERORR","OK") -> OK
A23: 151 | B23: Customer_151 | C23: ORD-56552 | D23: 45839 | E23: Comics | F23: =VLOOKUP(E23,Mapping!$A$1:$B$20,2,FALSE) -> Books | G23: 2 | H23: =IF(AND(G23<0,G23<>$N$4),"ERORR","OK") -> OK | I23: =ISNUMBER(G23) -> TRUE | J23: 457.16 | K23: =IF(OR(Table1[[#This Row],[Price]]>$S$20,Table1[[#This Row],[Price]]<$T$19),"Outlier","OK") -> OK | L23: =ISNUMBER(J23) -> TRUE | M23: PayPal | N23: Processing | O23: =Table1[[#This Row],[Price]]*Table1[[#This Row],[Quantity]] -> 914.32 | P23: =IF(AND(O23<0,O23<>N39),"ERORR","OK") -> OK
A24: 148 | B24: Customer_148 | C24: ORD-38423 | D24: 45729 | E24: Tennis Racket | F24: =VLOOKUP(E24,Mapping!$A$1:$B$20,2,FALSE) -> Sports | G24: 1 | H24: =IF(AND(G24<0,G24<>$N$4),"ERORR","OK") -> OK | I24: =ISNUMBER(G24) -> TRUE | J24: 660.98 | K24: =IF(OR(Table1[[#This Row],[Price]]>$S$20,Table1[[#This Row],[Price]]<$T$19),"Outlier","OK") -> OK | L24: =ISNUMBER(J24) -> TRUE | M24: Cash on Delivery | N24: Returned | O24: 0 | P24: =IF(AND(O24<0,O24<>N40),"ERORR","OK") -> OK
A25: 136 | B25: Customer_136 | C25: ORD-20985 | D25: 45820 | E25: Headphones | F25: =VLOOKUP(E25,Mapping!$A$1:$B$20,2,FALSE) -> Electronics | G25: 1 | H25: =IF(AND(G25<0,G25<>$N$4),"ERORR","OK") -> OK | I25: =ISNUMBER(G25) -> TRUE | J25: 696.71 | K25: =IF(OR(Table1[[#This Row],[Price]]>$S$20,Table1[[#This Row],[Price]]<$T$19),"Outlier","OK") -> OK | L25: =ISNUMBER(J25) -> TRUE | M25: Credit Card | N25: Delivered | O25: =Table1[[#This Row],[Price]]*Table1[[#This Row],[Quantity]] -> 696.71 | P25: =IF(AND(O25<0,O25<>N42),"ERORR","OK") -> OK
A26: 152 | B26: Customer_152 | C26: ORD-72869 | D26: 45922 | E26: Lamp | F26: =VLOOKUP(E26,Mapping!$A$1:$B$20,2,FALSE) -> Home | G26: 3 | H26: =IF(AND(G26<0,G26<>$N$4),"ERORR","OK") -> OK | I26: =ISNUMBER(G26) -> TRUE | J26: 233.11 | K26: =IF(OR(Table1[[#This Row],[Price]]>$S$20,Table1[[#This Row],[Price]]<$T$19),"Outlier","OK") -> OK | L26: =ISNUMBER(J26) -> TRUE | M26: PayPal | N26: Returned | O26: 0 | P26: =IF(AND(O26<0,O26<>N43),"ERORR","OK") -> OK
A27: 163 | B27: Customer_163 | C27: ORD-24378 | D27: 44931 | E27: Smartwatch | F27: =VLOOKUP(E27,Mapping!$A$1:$B$20,2,FALSE) -> Electronics | G27: 3 | H27: =IF(AND(G27<0,G27<>$N$4),"ERORR","OK") -> OK | I27: =ISNUMBER(G27) -> TRUE | J27: 235.26 | K27: =IF(OR(Table1[[#This Row],[Price]]>$S$20,Table1[[#This Row],[Price]]<$T$19),"Outlier","OK") -> OK | L27: =ISNUMBER(J27) -> TRUE | M27: Cash on Delivery | N27: Shipped | O27: =Table1[[#This Row],[Price]]*Table1[[#This Row],[Quantity]] -> 705.78 | P27: =IF(AND(O27<0,O27<>N44),"ERORR","OK") -> OK
A28: 174 | B28: Customer_174 | C28: ORD-16766 | D28: 45920 | E28: Microwave | F28: =VLOOKUP(E28,Mapping!$A$1:$B$20,2,FALSE) -> Home | G28: 4 | H28: =IF(AND(G28<0,G28<>$N$4),"ERORR","OK") -> OK | I28: =ISNUMBER(G28) -> TRUE | J28: 187.48 | K28: =IF(OR(Table1[[#This Row],[Price]]>$S$20,Table1[[#This Row],[Price]]<$T$19),"Outlier","OK") -> OK | L28: =ISNUMBER(J28) -> TRUE | M28: Credit Card | N28: Returned | O28: 0 | P28: =IF(AND(O28<0,O28<>N45),"ERORR","OK") -> OK
A29: 189 | B29: Customer_189 | C29: ORD-30627 | D29: 45883 | E29: Lamp | F29: =VLOOKUP(E29,Mapping!$A$1:$B$20,2,FALSE) -> Home | G29: 1 | H29: =IF(AND(G29<0,G29<>$N$4),"ERORR","OK") -> OK | I29: =ISNUMBER(G29) -> TRUE | J29: 814.68 | K29: =IF(OR(Table1[[#This Row],[Price]]>$S$20,Table1[[#This Row],[Price]]<$T$19),"Outlier","OK") -> OK | L29: =ISNUMBER(J29) -> TRUE | M29: Cash on Delivery | N29: Returned | O29: 0 | P29: =IF(AND(O29<0,O29<>N46),"ERORR","OK") -> OK
A30: 114 | B30: Customer_114 | C30: ORD-77417 | D30: 44931 | E30: Smartphone | F30: =VLOOKUP(E30,Mapping!$A$1:$B$20,2,FALSE) -> Electronics | G30: 2 | H30: =IF(AND(G30<0,G30<>$N$4),"ERORR","OK") -> OK | I30: =ISNUMBER(G30) -> TRUE | J30: 413.13 | K30: =IF(OR(Table1[[#This Row],[Price]]>$S$20,Table1[[#This Row],[Price]]<$T$19),"Outlier","OK") -> OK | L30: =ISNUMBER(J30) -> TRUE | M30: Cash on Delivery | N30: Shipped | O30: =Table1[[#This Row],[Price]]*Table1[[#This Row],[Quantity]] -> 826.26 | P30: =IF(AND(O30<0,O30<>N47),"ERORR","OK") -> OK
A31: 180 | B31: Customer_180 | C31: ORD-86629 | D31: 45742 | E31: Laptop | F31: =VLOOKUP(E31,Mapping!$A$1:$B$20,2,FALSE) -> Electronics | G31: 2 | H31: =IF(AND(G31<0,G31<>$N$4),"ERORR","OK") -> OK | I31: =ISNUMBER(G31) -> TRUE | J31: 418.38 | K31: =IF(OR(Table1[[#This Row],[Price]]>$S$20,Table1[[#This Row],[Price]]<$T$19),"Outlier","OK") -> OK | L31: =ISNUMBER(J31) -> TRUE | M31: Credit Card | N31: Processing | O31: =Table1[[#This Row],[Price]]*Table1[[#This Row],[Quantity]] -> 836.76 | P31: =IF(AND(O31<0,O31<>N47),"ERORR","OK") -> OK
A32: 161 | B32: Customer_161 | C32: ORD-27653 | D32: 45641 | E32: Science | F32: =VLOOKUP(E32,Mapping!$A$1:$B$20,2,FALSE) -> Books | G32: 4 | H32: =IF(AND(G32<0,G32<>$N$4),"ERORR","OK") -> OK | I32: =ISNUMBER(G32) -> TRUE | J32: 209.32 | K32: =IF(OR(Table1[[#This Row],[Price]]>$S$20,Table1[[#This Row],[Price]]<$T$19),"Outlier","OK") -> OK | L32: =ISNUMBER(J32) -> TRUE | M32: Bank Transfer | N32: Shipped | O32: =Table1[[#This Row],[Price]]*Table1[[#This Row],[Quantity]] -> 837.28 | P32: =IF(AND(O32<0,O32<>N47),"ERORR","OK") -> OK
A33: 109 | B33: Customer_109 | C33: ORD-18512 | D33: 45780 | E33: Tennis Racket | F33: =VLOOKUP(E33,Mapping!$A$1:$B$20,2,FALSE) -> Sports | G33: 5 | H33: =IF(AND(G33<0,G33<>$N$4),"ERORR","OK") -> OK | I33: =ISNUMBER(G33) -> TRUE | J33: 168.34 | K33: =IF(OR(Table1[[#This Row],[Price]]>$S$20,Table1[[#This Row],[Price]]<$T$19),"Outlier","OK") -> OK | L33: =ISNUMBER(J33) -> TRUE | M33: Credit Card | N33: Shipped | O33: =Table1[[#This Row],[Price]]*Table1[[#This Row],[Quantity]] -> 841.7 | P33: =IF(AND(O33<0,O33<>Table1[[#This Row],[Status]]),"ERORR","OK") -> OK
A34: 165 | B34: Customer_165 | C34: ORD-55695 | D34: 45604 | E34: Shoes | F34: =VLOOKUP(E34,Mapping!$A$1:$B$20,2,FALSE) -> Clothings | G34: 2 | H34: =IF(AND(G34<0,G34<>$N$4),"ERORR","OK") -> OK | I34: =ISNUMBER(G34) -> TRUE | J34: 645 | K34: =IF(OR(Table1[[#This Row],[Price]]>$S$20,Table1[[#This Row],[Price]]<$T$19),"Outlier","OK") -> OK | L34: =ISNUMBER(J34) -> TRUE | M34: Credit Card | N34: Delivered | O34: =Table1[[#This Row],[Price]]*Table1[[#This Row],[Quantity]] -> 1290 | P34: =IF(AND(O34<0,O34<>N50),"ERORR","OK") -> OK
A35: 190 | B35: Customer_190 | C35: ORD-38469 | D35: 45837 | E35: Vacuum | F35: =VLOOKUP(E35,Mapping!$A$1:$B$20,2,FALSE) -> Home | G35: 1 | H35: =IF(AND(G35<0,G35<>$N$4),"ERORR","OK") -> OK | I35: =ISNUMBER(G35) -> TRUE | J35: 920.37 | K35: =IF(OR(Table1[[#This Row],[Price]]>$S$20,Table1[[#This Row],[Price]]<$T$19),"Outlier","OK") -> OK | L35: =ISNUMBER(J35) -> TRUE | M35: Bank Transfer | N35: Processing | O35: =Table1[[#This Row],[Price]]*Table1[[#This Row],[Quantity]] -> 920.37 | P35: =IF(AND(O35<0,O35<>N50),"ERORR","OK") -> OK
A36: 158 | B36: Customer_158 | C36: ORD-35817 | D36: 45752 | E36: Smartwatch | F36: =VLOOKUP(E36,Mapping!$A$1:$B$20,2,FALSE) -> Electronics | G36: 1 | H36: =IF(AND(G36<0,G36<>$N$4),"ERORR","OK") -> OK | I36: =ISNUMBER(G36) -> TRUE | J36: 933.58 | K36: =IF(OR(Table1[[#This Row],[Price]]>$S$20,Table1[[#This Row],[Price]]<$T$19),"Outlier","OK") -> OK | L36: =ISNUMBER(J36) -> TRUE | M36: Cash on Delivery | N36: Shipped | O36: =Table1[[#This Row],[Price]]*Table1[[#This Row],[Quantity]] -> 933.58 | P36: =IF(AND(O36<0,O36<>N51),"ERORR","OK") -> OK
A37: 198 | B37: Customer_198 | C37: ORD-14608 | D37: 45865 | E37: Vacuum | F37: =VLOOKUP(E37,Mapping!$A$1:$B$20,2,FALSE) -> Home | G37: 2 | H37: =IF(AND(G37<0,G37<>$N$4),"ERORR","OK") -> OK | I37: =ISNUMBER(G37) -> TRUE | J37: 497.01 | K37: =IF(OR(Table1[[#This Row],[Price]]>$S$20,Table1[[#This Row],[Price]]<$T$19),"Outlier","OK") -> OK | L37: =ISNUMBER(J37) -> TRUE | M37: Cash on Delivery | N37: Shipped | O37: =Table1[[#This Row],[Price]]*Table1[[#This Row],[Quantity]] -> 994.02 | P37: =IF(AND(O37<0,O37<>N52),"ERORR","OK") -> OK
A38: 185 | B38: Customer_185 | C38: ORD-57123 | D38: 45883 | E38: Football | F38: =VLOOKUP(E38,Mapping!$A$1:$B$20,2,FALSE) -> Sports | G38: 2 | H38: =IF(AND(G38<0,G38<>$N$4),"ERORR","OK") -> OK | I38: =ISNUMBER(G38) -> TRUE | J38: 730.92 | K38: =IF(OR(Table1[[#This Row],[Price]]>$S$20,Table1[[#This Row],[Price]]<$T$19),"Outlier","OK") -> OK | L38: =ISNUMBER(J38) -> TRUE | M38: Cash on Delivery | N38: Cancelled | O38: 0 | P38: =IF(AND(O38<0,O38<>N54),"ERORR","OK") -> OK
A39: 157 | B39: Customer_157 | C39: ORD-34407 | D39: 45967 | E39: Jacket | F39: =VLOOKUP(E39,Mapping!$A$1:$B$20,2,FALSE) -> Clothings | G39: 4 | H39: =IF(AND(G39<0,G39<>$N$4),"ERORR","OK") -> OK | I39: =ISNUMBER(G39) -> TRUE | J39: 275.1 | K39: =IF(OR(Table1[[#This Row],[Price]]>$S$20,Table1[[#This Row],[Price]]<$T$19),"Outlier","OK") -> OK | L39: =ISNUMBER(J39) -> TRUE | M39: Bank Transfer | N39: Processing | O39: =Table1[[#This Row],[Price]]*Table1[[#This Row],[Quantity]] -> 1100.4 | P39: =IF(AND(O39<0,O39<>N55),"ERORR","OK") -> OK
A40: 122 | B40: Customer_122 | C40: ORD-21443 | D40: 45793 | E40: Microwave | F40: =VLOOKUP(E40,Mapping!$A$1:$B$20,2,FALSE) -> Home | G40: 2 | H40: =IF(AND(G40<0,G40<>$N$4),"ERORR","OK") -> OK | I40: =ISNUMBER(G40) -> TRUE | J40: 556.93 | K40: =IF(OR(Table1[[#This Row],[Price]]>$S$20,Table1[[#This Row],[Price]]<$T$19),"Outlier","OK") -> OK | L40: =ISNUMBER(J40) -> TRUE | M40: PayPal | N40: Shipped | O40: =Table1[[#This Row],[Price]]*Table1[[#This Row],[Quantity]] -> 1113.86 | P40: =IF(AND(O40<0,O40<>N55),"ERORR","OK") -> OK
A41: 115 | B41: Customer_115 | C41: ORD-72778 | D41: 45667 | E41: Fiction | F41: =VLOOKUP(E41,Mapping!$A$1:$B$20,2,FALSE) -> Books | G41: 2 | H41: =IF(AND(G41<0,G41<>$N$4),"ERORR","OK") -> OK | I41: =ISNUMBER(G41) -> TRUE | J41: 796.84 | K41: =IF(OR(Table1[[#This Row],[Price]]>$S$20,Table1[[#This Row],[Price]]<$T$19),"Outlier","OK") -> OK | L41: =ISNUMBER(J41) -> TRUE | M41: Cash on Delivery | N41: Returned | O41: 0 | P41: =IF(AND(O41<0,O41<>N55),"ERORR","OK") -> OK
A42: 153 | B42: Customer_153 | C42: ORD-29721 | D42: 45854 | E42: Yoga Mat | F42: =VLOOKUP(E42,Mapping!$A$1:$B$20,2,FALSE) -> Sports | G42: 4 | H42: =IF(AND(G42<0,G42<>$N$4),"ERORR","OK") -> OK | I42: =ISNUMBER(G42) -> TRUE | J42: 278.9 | K42: =IF(OR(Table1[[#This Row],[Price]]>$S$20,Table1[[#This Row],[Price]]<$T$19),"Outlier","OK") -> OK | L42: =ISNUMBER(J42) -> TRUE | M42: Cash on Delivery | N42: Processing | O42: =Table1[[#This Row],[Price]]*Table1[[#This Row],[Quantity]] -> 1115.6 | P42: =IF(AND(O42<0,O42<>N57),"ERORR","OK") -> OK
A43: 166 | B43: Customer_166 | C43: ORD-97756 | D43: 45841 | E43: T-shirt | F43: =VLOOKUP(E43,Mapping!$A$1:$B$20,2,FALSE) -> Clothings | G43: 2 | H43: =IF(AND(G43<0,G43<>$N$4),"ERORR","OK") -> OK | I43: =ISNUMBER(G43) -> TRUE | J43: 569.38 | K43: =IF(OR(Table1[[#This Row],[Price]]>$S$20,Table1[[#This Row],[Price]]<$T$19),"Outlier","OK") -> OK | L43: =ISNUMBER(J43) -> TRUE | M43: Cash on Delivery | N43: Shipped | O43: =Table1[[#This Row],[Price]]*Table1[[#This Row],[Quantity]] -> 1138.76 | P43: =IF(AND(O43<0,O43<>N58),"ERORR","OK") -> OK
A44: 103 | B44: Customer_103 | C44: ORD-57811 | D44: 45735 | E44: Science | F44: =VLOOKUP(E44,Mapping!$A$1:$B$20,2,FALSE) -> Books | G44: 5 | H44: =IF(AND(G44<0,G44<>$N$4),"ERORR","OK") -> OK | I44: =ISNUMBER(G44) -> TRUE | J44: 233.92 | K44: =IF(OR(Table1[[#This Row],[Price]]>$S$20,Table1[[#This Row],[Price]]<$T$19),"Outlier","OK") -> OK | L44: =ISNUMBER(J44) -> TRUE | M44: PayPal | N44: Processing | O44: =Table1[[#This Row],[Price]]*Table1[[#This Row],[Quantity]] -> 1169.6 | P44: =IF(AND(O44<0,O44<>N59),"ERORR","OK") -> OK
A45: 160 | B45: Customer_160 | C45: ORD-96037 | D45: 45660 | E45: Science | F45: =VLOOKUP(E45,Mapping!$A$1:$B$20,2,FALSE) -> Books | G45: 5 | H45: =IF(AND(G45<0,G45<>$N$4),"ERORR","OK") -> OK | I45: =ISNUMBER(G45) -> TRUE | J45: 242.52 | K45: =IF(OR(Table1[[#This Row],[Price]]>$S$20,Table1[[#This Row],[Price]]<$T$19),"Outlier","OK") -> OK | L45: =ISNUMBER(J45) -> TRUE | M45: Cash on Delivery | N45: Returned | O45: 0 | P45: =IF(AND(O45<0,O45<>N59),"ERORR","OK") -> OK
A46: 118 | B46: Customer_118 | C46: ORD-96061 | D46: 45808 | E46: Science | F46: =VLOOKUP(E46,Mapping!$A$1:$B$20,2,FALSE) -> Books | G46: 5 | H46: =IF(AND(G46<0,G46<>$N$4),"ERORR","OK") -> OK | I46: =ISNUMBER(G46) -> TRUE | J46: 247.82 | K46: =IF(OR(Table1[[#This Row],[Price]]>$S$20,Table1[[#This Row],[Price]]<$T$19),"Outlier","OK") -> OK | L46: =ISNUMBER(J46) -> TRUE | M46: PayPal | N46: Processing | O46: =Table1[[#This Row],[Price]]*Table1[[#This Row],[Quantity]] -> 1239.1 | P46: =IF(AND(O46<0,O46<>N61),"ERORR","OK") -> OK
A47: 139 | B47: Customer_139 | C47: ORD-38418 | D47: 45697 | E47: Smartphone | F47: =VLOOKUP(E47,Mapping!$A$1:$B$20,2,FALSE) -> Electronics | G47: 2 | H47: =IF(AND(G47<0,G47<>$N$4),"ERORR","OK") -> OK | I47: =ISNUMBER(G47) -> TRUE | J47: 681.38 | K47: =IF(OR(Table1[[#This Row],[Price]]>$S$20,Table1[[#This Row],[Price]]<$T$19),"Outlier","OK") -> OK | L47: =ISNUMBER(J47) -> TRUE | M47: Credit Card | N47: Cancelled | O47: 0 | P47: =IF(AND(O47<0,O47<>N63),"ERORR","OK") -> OK
A48: 146 | B48: Customer_146 | C48: ORD-32755 | D48: 45847 | E48: Basketball | F48: =VLOOKUP(E48,Mapping!$A$1:$B$20,2,FALSE) -> Sports | G48: 2 | H48: =IF(AND(G48<0,G48<>$N$4),"ERORR","OK") -> OK | I48: =ISNUMBER(G48) -> TRUE | J48: 705.42 | K48: =IF(OR(Table1[[#This Row],[Price]]>$S$20,Table1[[#This Row],[Price]]<$T$19),"Outlier","OK") -> OK | L48: =ISNUMBER(J48) -> TRUE | M48: Bank Transfer | N48: Processing | O48: =Table1[[#This Row],[Price]]*Table1[[#This Row],[Quantity]] -> 1410.84 | P48: =IF(AND(O48<0,O48<>N63),"ERORR","OK") -> OK
A49: 178 | B49: Customer_178 | C49: ORD-89906 | D49: 45918 | E49: Tennis Racket | F49: =VLOOKUP(E49,Mapping!$A$1:$B$20,2,FALSE) -> Sports | G49: 3 | H49: =IF(AND(G49<0,G49<>$N$4),"ERORR","OK") -> OK | I49: =ISNUMBER(G49) -> TRUE | J49: 472.14 | K49: =IF(OR(Table1[[#This Row],[Price]]>$S$20,Table1[[#This Row],[Price]]<$T$19),"Outlier","OK") -> OK | L49: =ISNUMBER(J49) -> TRUE | M49: PayPal | N49: Returned | O49: 0 | P49: =IF(AND(O49<0,O49<>N66),"ERORR","OK") -> OK
A50: 120 | B50: Customer_120 | C50: ORD-14659 | D50: 45821 | E50: Yoga Mat | F50: =VLOOKUP(E50,Mapping!$A$1:$B$20,2,FALSE) -> Sports | G50: 5 | H50: =IF(AND(G50<0,G50<>$N$4),"ERORR","OK") -> OK | I50: =ISNUMBER(G50) -> TRUE | J50: 300 | K50: =IF(OR(Table1[[#This Row],[Price]]>$S$20,Table1[[#This Row],[Price]]<$T$19),"Outlier","OK") -> OK | L50: =ISNUMBER(J50) -> TRUE | M50: Credit Card | N50: Cancelled | O50: 0 | P50: =IF(AND(O50<0,O50<>Table1[[#This Row],[Status]]),"ERORR","OK") -> OK
A51: 141 | B51: Customer_141 | C51: ORD-45059 | D51: 45701 | E51: Fiction | F51: =VLOOKUP(E51,Mapping!$A$1:$B$20,2,FALSE) -> Books | G51: 3 | H51: =IF(AND(G51<0,G51<>$N$4),"ERORR","OK") -> OK | I51: =ISNUMBER(G51) -> TRUE | J51: 546.04 | K51: =IF(OR(Table1[[#This Row],[Price]]>$S$20,Table1[[#This Row],[Price]]<$T$19),"Outlier","OK") -> OK | L51: =ISNUMBER(J51) -> TRUE | M51: Cash on Delivery | N51: Returned | O51: 0 | P51: =IF(AND(O51<0,O51<>N67),"ERORR","OK") -> OK
A52: 127 | B52: Customer_127 | C52: ORD-65482 | D52: 45789 | E52: Blender | F52: =VLOOKUP(E52,Mapping!$A$1:$B$20,2,FALSE) -> Home | G52: 5 | H52: =IF(AND(G52<0,G52<>$N$4),"ERORR","OK") -> OK | I52: =ISNUMBER(G52) -> TRUE | J52: 557 | K52: =IF(OR(Table1[[#This Row],[Price]]>$S$20,Table1[[#This Row],[Price]]<$T$19),"Outlier","OK") -> OK | L52: =ISNUMBER(J52) -> TRUE | M52: Bank Transfer | N52: Returned | O52: 0 | P52: =IF(AND(O52<0,O52<>N67),"ERORR","OK") -> OK
A53: 133 | B53: Customer_133 | C53: ORD-68182 | D53: 45631 | E53: Biography | F53: =VLOOKUP(E53,Mapping!$A$1:$B$20,2,FALSE) -> Books | G53: 5 | H53: =IF(AND(G53<0,G53<>$N$4),"ERORR","OK") -> OK | I53: =ISNUMBER(G53) -> TRUE | J53: 343.24 | K53: =IF(OR(Table1[[#This Row],[Price]]>$S$20,Table1[[#This Row],[Price]]<$T$19),"Outlier","OK") -> OK | L53: =ISNUMBER(J53) -> TRUE | M53: Credit Card | N53: Shipped | O53: =Table1[[#This Row],[Price]]*Table1[[#This Row],[Quantity]] -> 1716.2 | P53: =IF(AND(O53<0,O53<>N67),"ERORR","OK") -> OK
A54: 145 | B54: Customer_145 | C54: ORD-75314 | D54: 45047 | E54: Laptop | F54: =VLOOKUP(E54,Mapping!$A$1:$B$20,2,FALSE) -> Electronics | G54: 2 | H54: =IF(AND(G54<0,G54<>$N$4),"ERORR","OK") -> OK | I54: =ISNUMBER(G54) -> TRUE | J54: 860.99 | K54: =IF(OR(Table1[[#This Row],[Price]]>$S$20,Table1[[#This Row],[Price]]<$T$19),"Outlier","OK") -> OK | L54: =ISNUMBER(J54) -> TRUE | M54: Bank Transfer | N54: Returned | O54: 0 | P54: =IF(AND(O54<0,O54<>N70),"ERORR","OK") -> OK
A55: 111 | B55: Customer_111 | C55: ORD-72349 | D55: 45952 | E55: Comics | F55: =VLOOKUP(E55,Mapping!$A$1:$B$20,2,FALSE) -> Books | G55: 2 | H55: =IF(AND(G55<0,G55<>$N$4),"ERORR","OK") -> OK | I55: =ISNUMBER(G55) -> TRUE | J55: 865.77 | K55: =IF(OR(Table1[[#This Row],[Price]]>$S$20,Table1[[#This Row],[Price]]<$T$19),"Outlier","OK") -> OK | L55: =ISNUMBER(J55) -> TRUE | M55: Credit Card | N55: Returned | O55: 0 | P55: =IF(AND(O55<0,O55<>N71),"ERORR","OK") -> OK
A56: 119 | B56: Customer_119 | C56: ORD-76016 | D56: 45645 | E56: Basketball | F56: =VLOOKUP(E56,Mapping!$A$1:$B$20,2,FALSE) -> Sports | G56: 4 | H56: =IF(AND(G56<0,G56<>$N$4),"ERORR","OK") -> OK | I56: =ISNUMBER(G56) -> TRUE | J56: 438.19 | K56: =IF(OR(Table1[[#This Row],[Price]]>$S$20,Table1[[#This Row],[Price]]<$T$19),"Outlier","OK") -> OK | L56: =ISNUMBER(J56) -> TRUE | M56: Cash on Delivery | N56: Processing | O56: =Table1[[#This Row],[Price]]*Table1[[#This Row],[Quantity]] -> 1752.76 | P56: =IF(AND(O56<0,O56<>N70),"ERORR","OK") -> OK
A57: 173 | B57: Customer_173 | C57: ORD-42171 | D57: 45941 | E57: Lamp | F57: =VLOOKUP(E57,Mapping!$A$1:$B$20,2,FALSE) -> Home | G57: 5 | H57: =IF(AND(G57<0,G57<>$N$4),"ERORR","OK") -> OK | I57: =ISNUMBER(G57) -> TRUE | J57: 351.89 | K57: =IF(OR(Table1[[#This Row],[Price]]>$S$20,Table1[[#This Row],[Price]]<$T$19),"Outlier","OK") -> OK | L57: =ISNUMBER(J57) -> TRUE | M57: Credit Card | N57: Shipped | O57: =Table1[[#This Row],[Price]]*Table1[[#This Row],[Quantity]] -> 1759.45 | P57: =IF(AND(O57<0,O57<>N73),"ERORR","OK") -> OK
A58: 191 | B58: Customer_191 | C58: ORD-41810 | D58: 45856 | E58: Fiction | F58: =VLOOKUP(E58,Mapping!$A$1:$B$20,2,FALSE) -> Books | G58: 2 | H58: =IF(AND(G58<0,G58<>$N$4),"ERORR","OK") -> OK | I58: =ISNUMBER(G58) -> TRUE | J58: 881.02 | K58: =IF(OR(Table1[[#This Row],[Price]]>$S$20,Table1[[#This Row],[Price]]<$T$19),"Outlier","OK") -> OK | L58: =ISNUMBER(J58) -> TRUE | M58: Cash on Delivery | N58: Returned | O58: 0 | P58: =IF(AND(O58<0,O58<>N73),"ERORR","OK") -> OK
A59: 135 | B59: Customer_135 | C59: ORD-33656 | D59: 45697 | E59: Smartwatch | F59: =VLOOKUP(E59,Mapping!$A$1:$B$20,2,FALSE) -> Electronics | G59: 4 | H59: =IF(AND(G59<0,G59<>$N$4),"ERORR","OK") -> OK | I59: =ISNUMBER(G59) -> TRUE | J59: 446.19 | K59: =IF(OR(Table1[[#This Row],[Price]]>$S$20,Table1[[#This Row],[Price]]<$T$19),"Outlier","OK") -> OK | L59: =ISNUMBER(J59) -> TRUE | M59: Cash on Delivery | N59: Cancelled | O59: 0 | P59: =IF(AND(O59<0,O59<>N75),"ERORR","OK") -> OK
A60: 123 | B60: Customer_123 | C60: ORD-11314 | D60: 45936 | E60: Vacuum | F60: =VLOOKUP(E60,Mapping!$A$1:$B$20,2,FALSE) -> Home | G60: 3 | H60: =IF(AND(G60<0,G60<>$N$4),"ERORR","OK") -> OK | I60: =ISNUMBER(G60) -> TRUE | J60: 615.91 | K60: =IF(OR(Table1[[#This Row],[Price]]>$S$20,Table1[[#This Row],[Price]]<$T$19),"Outlier","OK") -> OK | L60: =ISNUMBER(J60) -> TRUE | M60: Cash on Delivery | N60: Cancelled | O60: 0 | P60: =IF(AND(O60<0,O60<>N76),"ERORR","OK") -> OK
A61: 199 | B61: Customer_199 | C61: ORD-82922 | D61: 45679 | E61: Blender | F61: =VLOOKUP(E61,Mapping!$A$1:$B$20,2,FALSE) -> Home | G61: 5 | H61: =IF(AND(G61<0,G61<>$N$4),"ERORR","OK") -> OK | I61: =ISNUMBER(G61) -> TRUE | J61: 569 | K61: =IF(OR(Table1[[#This Row],[Price]]>$S$20,Table1[[#This Row],[Price]]<$T$19),"Outlier","OK") -> OK | L61: =ISNUMBER(J61) -> TRUE | M61: Credit Card | N61: Shipped | O61: =Table1[[#This Row],[Price]]*Table1[[#This Row],[Quantity]] -> 2845 | P61: =IF(AND(O61<0,O61<>N75),"ERORR","OK") -> OK
A62: 172 | B62: Customer_172 | C62: ORD-48008 | D62: 45614 | E62: Comics | F62: =VLOOKUP(E62,Mapping!$A$1:$B$20,2,FALSE) -> Books | G62: 2 | H62: =IF(AND(G62<0,G62<>$N$4),"ERORR","OK") -> OK | I62: =ISNUMBER(G62) -> TRUE | J62: 942.76 | K62: =IF(OR(Table1[[#This Row],[Price]]>$S$20,Table1[[#This Row],[Price]]<$T$19),"Outlier","OK") -> OK | L62: =ISNUMBER(J62) -> TRUE | M62: Bank Transfer | N62: Returned | O62: 0 | P62: =IF(AND(O62<0,O62<>Table1[[#This Row],[Status]]),"ERORR","OK") -> OK
A63: 110 | B63: Customer_110 | C63: ORD-61020 | D63: 45926 | E63: Basketball | F63: =VLOOKUP(E63,Mapping!$A$1:$B$20,2,FALSE) -> Sports | G63: 5 | H63: =IF(AND(G63<0,G63<>$N$4),"ERORR","OK") -> OK | I63: =ISNUMBER(G63) -> TRUE | J63: 400 | K63: =IF(OR(Table1[[#This Row],[Price]]>$S$20,Table1[[#This Row],[Price]]<$T$19),"Outlier","OK") -> OK | L63: =ISNUMBER(J63) -> TRUE | M63: Cash on Delivery | N63: Cancelled | O63: 0 | P63: =IF(AND(O63<0,O63<>N79),"ERORR","OK") -> OK
A64: 171 | B64: Customer_171 | C64: ORD-99790 | D64: 45632 | E64: Shoes | F64: =VLOOKUP(E64,Mapping!$A$1:$B$20,2,FALSE) -> Clothings | G64: 3 | H64: =IF(AND(G64<0,G64<>$N$4),"ERORR","OK") -> OK | I64: =ISNUMBER(G64) -> TRUE | J64: 832 | K64: =IF(OR(Table1[[#This Row],[Price]]>$S$20,Table1[[#This Row],[Price]]<$T$19),"Outlier","OK") -> OK | L64: =ISNUMBER(J64) -> TRUE | M64: PayPal | N64: Processing | O64: =Table1[[#This Row],[Price]]*Table1[[#This Row],[Quantity]] -> 2496 | P64: =IF(AND(O64<0,O64<>N78),"ERORR","OK") -> OK
A65: 121 | B65: Customer_121 | C65: ORD-80067 | D65: 45941 | E65: Basketball | F65: =VLOOKUP(E65,Mapping!$A$1:$B$20,2,FALSE) -> Sports | G65: 4 | H65: =IF(AND(G65<0,G65<>$N$4),"ERORR","OK") -> OK | I65: =ISNUMBER(G65) -> TRUE | J65: 523.01 | K65: =IF(OR(Table1[[#This Row],[Price]]>$S$20,Table1[[#This Row],[Price]]<$T$19),"Outlier","OK") -> OK | L65: =ISNUMBER(J65) -> TRUE | M65: Credit Card | N65: Delivered | O65: =Table1[[#This Row],[Price]]*Table1[[#This Row],[Quantity]] -> 2092.04 | P65: =IF(AND(O65<0,O65<>N81),"ERORR","OK") -> OK
A66: 182 | B66: Customer_182 | C66: ORD-79672 | D66: 45872 | E66: Shoes | F66: =VLOOKUP(E66,Mapping!$A$1:$B$20,2,FALSE) -> Clothings | G66: 4 | H66: =IF(AND(G66<0,G66<>$N$4),"ERORR","OK") -> OK | I66: =ISNUMBER(G66) -> TRUE | J66: 701 | K66: =IF(OR(Table1[[#This Row],[Price]]>$S$20,Table1[[#This Row],[Price]]<$T$19),"Outlier","OK") -> OK | L66: =ISNUMBER(J66) -> TRUE | M66: PayPal | N66: Processing | O66: =Table1[[#This Row],[Price]]*Table1[[#This Row],[Quantity]] -> 2804 | P66: =IF(AND(O66<0,O66<>N81),"ERORR","OK") -> OK
A67: 140 | B67: Customer_140 | C67: ORD-67096 | D67: 45714 | E67: Fiction | F67: =VLOOKUP(E67,Mapping!$A$1:$B$20,2,FALSE) -> Books | G67: 4 | H67: =IF(AND(G67<0,G67<>$N$4),"ERORR","OK") -> OK | I67: =ISNUMBER(G67) -> TRUE | J67: 588.98 | K67: =IF(OR(Table1[[#This Row],[Price]]>$S$20,Table1[[#This Row],[Price]]<$T$19),"Outlier","OK") -> OK | L67: =ISNUMBER(J67) -> TRUE | M67: Credit Card | N67: Returned | O67: 0 | P67: =IF(AND(O67<0,O67<>N83),"ERORR","OK") -> OK
A68: 147 | B68: Customer_147 | C68: ORD-80707 | D68: 45778 | E68: Jacket | F68: =VLOOKUP(E68,Mapping!$A$1:$B$20,2,FALSE) -> Clothings | G68: 4 | H68: =IF(AND(G68<0,G68<>$N$4),"ERORR","OK") -> OK | I68: =ISNUMBER(G68) -> TRUE | J68: 596.15 | K68: =IF(OR(Table1[[#This Row],[Price]]>$S$20,Table1[[#This Row],[Price]]<$T$19),"Outlier","OK") -> OK | L68: =ISNUMBER(J68) -> TRUE | M68: Cash on Delivery | N68: Shipped | O68: =Table1[[#This Row],[Price]]*Table1[[#This Row],[Quantity]] -> 2384.6 | P68: =IF(AND(O68<0,O68<>N84),"ERORR","OK") -> OK
A69: 188 | B69: Customer_188 | C69: ORD-58590 | D69: 45615 | E69: Microwave | F69: =VLOOKUP(E69,Mapping!$A$1:$B$20,2,FALSE) -> Home | G69: 5 | H69: =IF(AND(G69<0,G69<>$N$4),"ERORR","OK") -> OK | I69: =ISNUMBER(G69) -> TRUE | J69: 504.05 | K69: =IF(OR(Table1[[#This Row],[Price]]>$S$20,Table1[[#This Row],[Price]]<$T$19),"Outlier","OK") -> OK | L69: =ISNUMBER(J69) -> TRUE | M69: Cash on Delivery | N69: Shipped | O69: =Table1[[#This Row],[Price]]*Table1[[#This Row],[Quantity]] -> 2520.25 | P69: =IF(AND(O69<0,O69<>N84),"ERORR","OK") -> OK
A70: 179 | B70: Customer_179 | C70: ORD-99328 | D70: 45903 | E70: Yoga Mat | F70: =VLOOKUP(E70,Mapping!$A$1:$B$20,2,FALSE) -> Sports | G70: 3 | H70: =IF(AND(G70<0,G70<>$N$4),"ERORR","OK") -> OK | I70: =ISNUMBER(G70) -> TRUE | J70: 868.67 | K70: =IF(OR(Table1[[#This Row],[Price]]>$S$20,Table1[[#This Row],[Price]]<$T$19),"Outlier","OK") -> OK | L70: =ISNUMBER(J70) -> TRUE | M70: PayPal | N70: Delivered | O70: =Table1[[#This Row],[Price]]*Table1[[#This Row],[Quantity]] -> 2606.01 | P70: =IF(AND(O70<0,O70<>N87),"ERORR","OK") -> OK
A71: 187 | B71: Customer_187 | C71: ORD-41292 | D71: 45615 | E71: Smartphone | F71: =VLOOKUP(E71,Mapping!$A$1:$B$20,2,FALSE) -> Electronics | G71: 3 | H71: =IF(AND(G71<0,G71<>$N$4),"ERORR","OK") -> OK | I71: =ISNUMBER(G71) -> TRUE | J71: 882.96 | K71: =IF(OR(Table1[[#This Row],[Price]]>$S$20,Table1[[#This Row],[Price]]<$T$19),"Outlier","OK") -> OK | L71: =ISNUMBER(J71) -> TRUE | M71: Bank Transfer | N71: Returned | O71: 0 | P71: =IF(AND(O71<0,O71<>Table1[[#This Row],[Status]]),"ERORR","OK") -> OK
A72: 176 | B72: Customer_176 | C72: ORD-95794 | D72: 45860 | E72: Comics | F72: =VLOOKUP(E72,Mapping!$A$1:$B$20,2,FALSE) -> Books | G72: 5 | H72: =IF(AND(G72<0,G72<>$N$4),"ERORR","OK") -> OK | I72: =ISNUMBER(G72) -> TRUE | J72: 530.52 | K72: =IF(OR(Table1[[#This Row],[Price]]>$S$20,Table1[[#This Row],[Price]]<$T$19),"Outlier","OK") -> OK | L72: =ISNUMBER(J72) -> TRUE | M72: Cash on Delivery | N72: Shipped | O72: =Table1[[#This Row],[Price]]*Table1[[#This Row],[Quantity]] -> 2652.6 | P72: =IF(AND(O72<0,O72<>N88),"ERORR","OK") -> OK
A73: 128 | B73: Customer_128 | C73: ORD-12270 | D73: 45606 | E73: Lamp | F73: =VLOOKUP(E73,Mapping!$A$1:$B$20,2,FALSE) -> Home | G73: 3 | H73: =IF(AND(G73<0,G73<>$N$4),"ERORR","OK") -> OK | I73: =ISNUMBER(G73) -> TRUE | J73: 898.69 | K73: =IF(OR(Table1[[#This Row],[Price]]>$S$20,Table1[[#This Row],[Price]]<$T$19),"Outlier","OK") -> OK | L73: =ISNUMBER(J73) -> TRUE | M73: Bank Transfer | N73: Delivered | O73: =Table1[[#This Row],[Price]]*Table1[[#This Row],[Quantity]] -> 2696.07 | P73: =IF(AND(O73<0,O73<>N90),"ERORR","OK") -> OK
A74: 107 | B74: Customer_107 | C74: ORD-89122 | D74: 45660 | E74: Biography | F74: =VLOOKUP(E74,Mapping!$A$1:$B$20,2,FALSE) -> Books | G74: 5 | H74: =IF(AND(G74<0,G74<>$N$4),"ERORR","OK") -> OK | I74: =ISNUMBER(G74) -> TRUE | J74: 587.68 | K74: =IF(OR(Table1[[#This Row],[Price]]>$S$20,Table1[[#This Row],[Price]]<$T$19),"Outlier","OK") -> OK | L74: =ISNUMBER(J74) -> TRUE | M74: PayPal | N74: Returned | O74: 0 | P74: =IF(AND(O74<0,O74<>N89),"ERORR","OK") -> OK
A75: 129 | B75: Customer_129 | C75: ORD-48863 | D75: 45830 | E75: Science | F75: =VLOOKUP(E75,Mapping!$A$1:$B$20,2,FALSE) -> Books | G75: 4 | H75: =IF(AND(G75<0,G75<>$N$4),"ERORR","OK") -> OK | I75: =ISNUMBER(G75) -> TRUE | J75: 736.71 | K75: =IF(OR(Table1[[#This Row],[Price]]>$S$20,Table1[[#This Row],[Price]]<$T$19),"Outlier","OK") -> OK | L75: =ISNUMBER(J75) -> TRUE | M75: Bank Transfer | N75: Returned | O75: 0 | P75: =IF(AND(O75<0,O75<>Table1[[#This Row],[Status]]),"ERORR","OK") -> OK
A76: 134 | B76: Customer_134 | C76: ORD-16585 | D76: 45934 | E76: T-shirt | F76: =VLOOKUP(E76,Mapping!$A$1:$B$20,2,FALSE) -> Clothings | G76: 5 | H76: =IF(AND(G76<0,G76<>$N$4),"ERORR","OK") -> OK | I76: =ISNUMBER(G76) -> TRUE | J76: 591.53 | K76: =IF(OR(Table1[[#This Row],[Price]]>$S$20,Table1[[#This Row],[Price]]<$T$19),"Outlier","OK") -> OK | L76: =ISNUMBER(J76) -> TRUE | M76: PayPal | N76: Shipped | O76: =Table1[[#This Row],[Price]]*Table1[[#This Row],[Quantity]] -> 2957.65 | P76: =IF(AND(O76<0,O76<>N93),"ERORR","OK") -> OK
A77: 112 | B77: Customer_112 | C77: ORD-80867 | D77: 45718 | E77: Shoes | F77: =VLOOKUP(E77,Mapping!$A$1:$B$20,2,FALSE) -> Clothings | G77: 4 | H77: =IF(AND(G77<0,G77<>$N$4),"ERORR","OK") -> OK | I77: =ISNUMBER(G77) -> TRUE | J77: 866 | K77: =IF(OR(Table1[[#This Row],[Price]]>$S$20,Table1[[#This Row],[Price]]<$T$19),"Outlier","OK") -> OK | L77: =ISNUMBER(J77) -> TRUE | M77: Bank Transfer | N77: Delivered | O77: =Table1[[#This Row],[Price]]*Table1[[#This Row],[Quantity]] -> 3464 | P77: =IF(AND(O77<0,O77<>N93),"ERORR","OK") -> OK
A78: 125 | B78: Customer_125 | C78: ORD-23202 | D78: 45697 | E78: Comics | F78: =VLOOKUP(E78,Mapping!$A$1:$B$20,2,FALSE) -> Books | G78: 4 | H78: =IF(AND(G78<0,G78<>$N$4),"ERORR","OK") -> OK | I78: =ISNUMBER(G78) -> TRUE | J78: 765.69 | K78: =IF(OR(Table1[[#This Row],[Price]]>$S$20,Table1[[#This Row],[Price]]<$T$19),"Outlier","OK") -> OK | L78: =ISNUMBER(J78) -> TRUE | M78: PayPal | N78: Shipped | O78: =Table1[[#This Row],[Price]]*Table1[[#This Row],[Quantity]] -> 3062.76 | P78: =IF(AND(O78<0,O78<>N95),"ERORR","OK") -> OK
A79: 131 | B79: Customer_131 | C79: ORD-91396 | D79: 45819 | E79: Lamp | F79: =VLOOKUP(E79,Mapping!$A$1:$B$20,2,FALSE) -> Home | G79: 5 | H79: =IF(AND(G79<0,G79<>$N$4),"ERORR","OK") -> OK | I79: =ISNUMBER(G79) -> TRUE | J79: 616.63 | K79: =IF(OR(Table1[[#This Row],[Price]]>$S$20,Table1[[#This Row],[Price]]<$T$19),"Outlier","OK") -> OK | L79: =ISNUMBER(J79) -> TRUE | M79: PayPal | N79: Shipped | O79: =Table1[[#This Row],[Price]]*Table1[[#This Row],[Quantity]] -> 3083.15 | P79: =IF(AND(O79<0,O79<>N96),"ERORR","OK") -> OK
A80: 142 | B80: Customer_142 | C80: ORD-69018 | D80: 45960 | E80: Shoes | F80: =VLOOKUP(E80,Mapping!$A$1:$B$20,2,FALSE) -> Clothings | G80: 5 | H80: =IF(AND(G80<0,G80<>$N$4),"ERORR","OK") -> OK | I80: =ISNUMBER(G80) -> TRUE | J80: 816 | K80: =IF(OR(Table1[[#This Row],[Price]]>$S$20,Table1[[#This Row],[Price]]<$T$19),"Outlier","OK") -> OK | L80: =ISNUMBER(J80) -> TRUE | M80: Credit Card | N80: Shipped | O80: =Table1[[#This Row],[Price]]*Table1[[#This Row],[Quantity]] -> 4080 | P80: =IF(AND(O80<0,O80<>N97),"ERORR","OK") -> OK
A81: 126 | B81: Customer_126 | C81: ORD-11261 | D81: 45795 | E81: Shoes | F81: =VLOOKUP(E81,Mapping!$A$1:$B$20,2,FALSE) -> Clothings | G81: 4 | H81: =IF(AND(G81<0,G81<>$N$4),"ERORR","OK") -> OK | I81: =ISNUMBER(G81) -> TRUE | J81: 883 | K81: =IF(OR(Table1[[#This Row],[Price]]>$S$20,Table1[[#This Row],[Price]]<$T$19),"Outlier","OK") -> OK | L81: =ISNUMBER(J81) -> TRUE | M81: Bank Transfer | N81: Cancelled | O81: 0 | P81: =IF(AND(O81<0,O81<>N97),"ERORR","OK") -> OK
A82: 170 | B82: Customer_170 | C82: ORD-21530 | D82: 45933 | E82: Jeans | F82: =VLOOKUP(E82,Mapping!$A$1:$B$20,2,FALSE) -> Clothings | G82: 5 | H82: =IF(AND(G82<0,G82<>$N$4),"ERORR","OK") -> OK | I82: =ISNUMBER(G82) -> TRUE | J82: 741.63 | K82: =IF(OR(Table1[[#This Row],[Price]]>$S$20,Table1[[#This Row],[Price]]<$T$19),"Outlier","OK") -> OK | L82: =ISNUMBER(J82) -> TRUE | M82: Bank Transfer | N82: Processing | O82: =Table1[[#This Row],[Price]]*Table1[[#This Row],[Quantity]] -> 3708.15 | P82: =IF(AND(O82<0,O82<>N99),"ERORR","OK") -> OK
A83: 154 | B83: Customer_154 | C83: ORD-95990 | D83: 45709 | E83: Blender | F83: =VLOOKUP(E83,Mapping!$A$1:$B$20,2,FALSE) -> Home | G83: 5 | H83: =IF(AND(G83<0,G83<>$N$4),"ERORR","OK") -> OK | I83: =ISNUMBER(G83) -> TRUE | J83: 557 | K83: =IF(OR(Table1[[#This Row],[Price]]>$S$20,Table1[[#This Row],[Price]]<$T$19),"Outlier","OK") -> OK | L83: =ISNUMBER(J83) -> TRUE | M83: Cash on Delivery | N83: Cancelled | O83: 0 | P83: =IF(AND(O83<0,O83<>N100),"ERORR","OK") -> OK
A84: 195 | B84: Customer_195 | C84: ORD-82876 | D84: 45827 | E84: Biography | F84: =VLOOKUP(E84,Mapping!$A$1:$B$20,2,FALSE) -> Books | G84: 5 | H84: =IF(AND(G84<0,G84<>$N$4),"ERORR","OK") -> OK | I84: =ISNUMBER(G84) -> TRUE | J84: 817.46 | K84: =IF(OR(Table1[[#This Row],[Price]]>$S$20,Table1[[#This Row],[Price]]<$T$19),"Outlier","OK") -> OK | L84: =ISNUMBER(J84) -> TRUE | M84: Cash on Delivery | N84: Returned | O84: 0 | P84: =IF(AND(O84<0,O84<>N101),"ERORR","OK") -> OK
A85: 143 | B85: Customer_143 | C85: ORD-14329 | D85: 45849 | E85: T-shirt | F85: =VLOOKUP(E85,Mapping!$A$1:$B$20,2,FALSE) -> Clothings | G85: 5 | H85: =IF(AND(G85<0,G85<>$N$4),"ERORR","OK") -> OK | I85: =ISNUMBER(G85) -> TRUE | J85: 826.77 | K85: =IF(OR(Table1[[#This Row],[Price]]>$S$20,Table1[[#This Row],[Price]]<$T$19),"Outlier","OK") -> OK | L85: =ISNUMBER(J85) -> TRUE | M85: Bank Transfer | N85: Cancelled | O85: 0 | P85: =IF(AND(O85<0,O85<>N101),"ERORR","OK") -> OK
A86: 144 | B86: Customer_144 | C86: ORD-89452 | D86: 45684 | E86: Football | F86: =VLOOKUP(E86,Mapping!$A$1:$B$20,2,FALSE) -> Sports | G86: 5 | H86: =IF(AND(G86<0,G86<>$N$4),"ERORR","OK") -> OK | I86: =ISNUMBER(G86) -> TRUE | J86: 849.07 | K86: =IF(OR(Table1[[#This Row],[Price]]>$S$20,Table1[[#This Row],[Price]]<$T$19),"Outlier","OK") -> OK | L86: =ISNUMBER(J86) -> TRUE | M86: Bank Transfer | N86: Processing | O86: =Table1[[#This Row],[Price]]*Table1[[#This Row],[Quantity]] -> 4245.35 | P86: =IF(AND(O86<0,O86<>N101),"ERORR","OK") -> OK
A87: 149 | B87: Customer_149 | C87: ORD-95911 | D87: 45837 | E87: Comics | F87: =VLOOKUP(E87,Mapping!$A$1:$B$20,2,FALSE) -> Books | G87: 5 | H87: =IF(AND(G87<0,G87<>$N$4),"ERORR","OK") -> OK | I87: =ISNUMBER(G87) -> TRUE | J87: 896.38 | K87: =IF(OR(Table1[[#This Row],[Price]]>$S$20,Table1[[#This Row],[Price]]<$T$19),"Outlier","OK") -> OK | L87: =ISNUMBER(J87) -> TRUE | M87: Bank Transfer | N87: Cancelled | O87: 0 | P87: =IF(AND(O87<0,O87<>N103),"ERORR","OK") -> OK
A88: 194 | B88: Customer_194 | C88: ORD-69764 | D88: 45698 | E88: Lamp | F88: =VLOOKUP(E88,Mapping!$A$1:$B$20,2,FALSE) -> Home | G88: 5 | H88: =IF(AND(G88<0,G88<>$N$4),"ERORR","OK") -> OK | I88: =ISNUMBER(G88) -> TRUE | J88: 944.54 | K88: =IF(OR(Table1[[#This Row],[Price]]>$S$20,Table1[[#This Row],[Price]]<$T$19),"Outlier","OK") -> OK | L88: =ISNUMBER(J88) -> TRUE | M88: Cash on Delivery | N88: Returned | O88: 0 | P88: =IF(AND(O88<0,O88<>N105),"ERORR","OK") -> OK
A89: 117 | B89: Customer_117 | C89: ORD-72751 | D89: 45700 | E89: Blender | F89: =VLOOKUP(E89,Mapping!$A$1:$B$20,2,FALSE) -> Home | G89: 2 | H89: =IF(AND(G89<0,G89<>$N$4),"ERORR","OK") -> OK | I89: =ISNUMBER(G89) -> TRUE | J89: 538 | K89: =IF(OR(Table1[[#This Row],[Price]]>$S$20,Table1[[#This Row],[Price]]<$T$19),"Outlier","OK") -> OK | L89: =ISNUMBER(J89) -> TRUE | M89: Cash on Delivery | N89: Processing | O89: =Table1[[#This Row],[Price]]*Table1[[#This Row],[Quantity]] -> 1076 | P89: =IF(AND(O89<0,O89<>N106),"ERORR","OK") -> OK

Sheet Mapping
A1: Smartwatch | B1: Electronics | D1: Customer_Name
A2: Smartphone | B2: Electronics | D2: Customer_163
A3: Laptop | B3: Electronics | D3: Customer_114
A4: Shoes | B4: Clothings | D4: Customer_145
A5: Lamp | B5: Home | D5: Customer_165
A6: Comics | B6: Books | D6: Customer_128
A7: Microwave | B7: Home | D7: Customer_172
A8: Tennis Racket | B8: Sports | D8: Customer_187
A9: Blender | B9: Home | D9: Customer_188
A10: Yoga Mat | B10: Sports | D10: Customer_105
A11: Jeans | B11: Clothings | D11: Customer_100
A12: Biography | B12: Books | D12: Customer_150
... A20: T-shirt | B20: Clothings | D20: Customer_160
D21: Customer_115
D22: Customer_199
D23: Customer_144
D24: Customer_106
D25: Customer_125
D26: Customer_135
D27: Customer_139
D28: Customer_164
D29: Customer_194
D30: Customer_117
D31: Customer_141
D32: Customer_184
... D93: Customer_157

Sheet Backup of Raw Data
A1: ID | B1: Customer_Name | C1: Order_ID | D1: Order_Date | E1: Order_Date | F1: Order_Date | G1: Product | H1: Category | I1: Quantity | J1: Price | L1: Payment_Method | M1: Status | N1: Total | O1: Q1 | P1: =_xlfn.QUARTILE.INC(F:F,1) -> 45697
A2: 163 | B2: Customer_163 | C2: ORD-24378 | D2: 44931 | E2: =ISNUMBER(D2) -> TRUE | F2: 44931 | G2: Smartwatch | H2: Electronics | I2: 3 | J2: 235.26 | L2: Cash on Delivery | M2: Shipped | N2: 705.78 | O2: q3 | P2: =_xlfn.QUARTILE.INC(F:F,3) -> 45875
A3: 114 | B3: Customer_114 | C3: ORD-77417 | D3: 44931 | E3: =ISNUMBER(D3) -> TRUE | F3: =DATE(RIGHT(D3,4),MONTH(1&LEFT(D3,3)),MID(D3,5,2)) -> 1107386 | G3: Smartphone | H3: Electronics | I3: 2 | J3: 413.13 | L3: Cash on Delivery | M3: Shipped | N3: 826.26 | O3: IQR | P3: =P2-P1 -> 178
A4: 145 | B4: Customer_145 | C4: ORD-75314 | D4: 45047 | E4: =ISNUMBER(D4) -> TRUE | F4: 45047 | G4: Laptop | H4: Electronics | I4: 2 | J4: 860.99 | L4: Bank Transfer | M4: Returned | N4: 1721.98 | O4: Lower | P4: =P1-(1.5*P3) -> 45430 | Q4: =ABS(P4) -> 45430
A5: 165 | B5: Customer_165 | C5: ORD-55695 | D5: 45604 | E5: =ISNUMBER(D5) -> TRUE | F5: 45604 | G5: Shoes | H5: Clothing | I5: 2 | J5: 443.13 | L5: Credit Card | M5: Delivered | N5: 886.26 | O5: Upper | P5: =P2+1.5*P3 -> 46142
A6: 128 | B6: Customer_128 | C6: ORD-12270 | D6: 45606 | E6: =ISNUMBER(D6) -> TRUE | F6: 45606 | G6: Lamp | H6: electronics | I6: 3 | J6: 898.69 | L6: Bank Transfer | M6: Delivered | N6: 2696.07
A7: 172 | B7: Customer_172 | C7: ORD-48008 | D7: 45614 | E7: =ISNUMBER(D7) -> TRUE | F7: 45614 | G7: Comics | H7: Books | I7: 2 | J7: 942.76 | L7: Bank Transfer | M7: Returned | N7: 1885.52
A8: 187 | B8: Customer_187 | C8: ORD-41292 | D8: 45615 | E8: =ISNUMBER(D8) -> TRUE | F8: 45615 | G8: Smartphone | H8: Electronics | I8: 3 | J8: 882.96 | L8: Bank Transfer | M8: Returned | N8: 2648.88
A9: 188 | B9: Customer_188 | C9: ORD-58590 | D9: 45615 | E9: =ISNUMBER(D9) -> TRUE | F9: 45615 | G9: Microwave | H9: Home | I9: 5 | J9: 504.05 | L9: Cash on Delivery | M9: Shipped | N9: 2520.25
A10: 105 | B10: Customer_105 | C10: ORD-22442 | D10: 45616 | E10: =ISNUMBER(D10) -> TRUE | F10: 45616 | G10: Tennis Racket | H10: Sports | I10: 3 | J10: 122.06 | L10: Cash on Delivery | M10: Cancelled | N10: 366.18
A11: 100 | B11: Customer_100 | C11: ORD-41285 | D11: 45618 | E11: =ISNUMBER(D11) -> TRUE | F11: 45618 | G11: Blender | H11: Home | I11: 3 | J11: 38 | L11: Cash on Delivery | M11: Shipped | N11: 114
A12: 150 | B12: Customer_150 | C12: ORD-76902 | D12: 45623 | E12: =ISNUMBER(D12) -> TRUE | F12: 45623 | G12: Yoga Mat | H12: Sports | I12: 1 | J12: 206.19 | L12: Credit Card | M12: Returned | N12: 206.19
A13: 156 | B13: Customer_156 | C13: ORD-34679 | D13: 45624 | E13: =ISNUMBER(D13) -> TRUE | F13: 45624 | G13: Jeans | H13: Clothing | I13: 2 | L13: Bank Transfer | M13: Shipped
A14: 133 | B14: Customer_133 | C14: ORD-68182 | D14: 45631 | E14: =ISNUMBER(D14) -> TRUE | F14: 45631 | G14: Biography | H14: nan | I14: 5 | J14: 343.24 | L14: Credit Card | M14: Shipped | N14: 1716.2
A15: 171 | B15: Customer_171 | C15: ORD-99790 | D15: 45632 | E15: =ISNUMBER(D15) -> TRUE | F15: 45632 | G15: Shoes | H15: Clothing | I15: 3 | J15: 688.68 | L15: PayPal | M15: Processing | N15: 2066.04
A16: 161 | B16: Customer_161 | C16: ORD-27653 | D16: 45641 | E16: =ISNUMBER(D16) -> TRUE | F16: 45641 | G16: Science | H16: Books | I16: 4 | J16: 209.32 | L16: Bank Transfer | M16: Shipped | N16: 837.28
A17: 119 | B17: Customer_119 | C17: ORD-76016 | D17: 45645 | E17: =ISNUMBER(D17) -> TRUE | F17: 45645 | G17: Basketball | H17: Sports | I17: 4 | J17: 438.19 | L17: Cash on Delivery | M17: Processing | N17: 1752.76
A18: 102 | B18: Customer_102 | C18: ORD-84355 | D18: 45649 | E18: =ISNUMBER(D18) -> TRUE | F18: 45649 | G18: Tennis Racket | H18: Sports | I18: 1 | J18: 389.05 | L18: PayPal | M18: Delivered | N18: 389.05
A19: 196 | B19: Customer_196 | C19: ORD-78384 | D19: 45649 | E19: =ISNUMBER(D19) -> TRUE | F19: 45649 | G19: Vacuum | H19: Home | J19: abd | L19: PayPal | M19: Delivered
A20: 181 | B20: Customer_181 | C20: ORD-54481 | D20: 45655 | E20: =ISNUMBER(D20) -> TRUE | F20: 45655 | G20: Smartphone | H20: nan | I20: 1 | J20: 266.48 | L20: Cash on Delivery | M20: Cancelled | N20: 266.48
A21: 107 | B21: Customer_107 | C21: ORD-89122 | D21: 45660 | E21: =ISNUMBER(D21) -> TRUE | F21: 45660 | G21: Biography | H21: Books | I21: 5 | J21: 587.68 | L21: PayPal | M21: Returned | N21: 2938.4
A22: 160 | B22: Customer_160 | C22: ORD-96037 | D22: 45660 | E22: =ISNUMBER(D22) -> TRUE | F22: 45660 | G22: Science | H22: Books | I22: 5 | J22: 242.52 | L22: Cash on Delivery | M22: Returned | N22: 1212.6
A23: 115 | B23: Customer_115 | C23: ORD-72778 | D23: 45667 | E23: =ISNUMBER(D23) -> TRUE | F23: 45667 | G23: Fiction | H23: Books | I23: 2 | J23: 796.84 | L23: Cash on Delivery | M23: Returned | N23: 1115.576
A24: 199 | B24: Customer_199 | C24: ORD-82922 | D24: 45679 | E24: =ISNUMBER(D24) -> TRUE | F24: 45679 | G24: Blender | H24: Home | I24: 5 | J24: 372.28 | L24: Credit Card | M24: Shipped | N24: 1861.4
A25: 144 | B25: Customer_144 | C25: ORD-89452 | D25: 45684 | E25: =ISNUMBER(D25) -> TRUE | F25: 45684 | G25: Football | H25: Sports | I25: 5 | J25: 849.07 | L25: Bank Transfer | M25: Processing | N25: 4245.35
A26: 106 | B26: Customer_106 | C26: ORD-25885 | D26: 45690 | E26: =ISNUMBER(D26) -> TRUE | F26: 45690 | G26: Blender | H26: Home | J26: 978.63 | L26: Bank Transfer | M26: Processing
A27: 125 | B27: Customer_125 | C27: ORD-23202 | D27: 45697 | E27: =ISNUMBER(D27) -> TRUE | F27: 45697 | G27: Comics | H27: Books | I27: 4 | J27: 765.69 | L27: PayPal | M27: Shipped | N27: 3062.76
A28: 135 | B28: Customer_135 | C28: ORD-33656 | D28: 45697 | E28: =ISNUMBER(D28) -> TRUE | F28: 45697 | G28: Smartwatch | H28: electronics | I28: 4 | J28: 446.19 | L28: Cash on Delivery | M28: Cancelled | N28: 1784.76
A29: 139 | B29: Customer_139 | C29: ORD-38418 | D29: 45697 | E29: =ISNUMBER(D29) -> TRUE | F29: 45697 | G29: Smartphone | H29: Electronics | I29: 2 | J29: 681.38 | L29: Credit Card | M29: Cancelled | N29: 1362.76
A30: 164 | B30: Customer_164 | C30: ORD-23010 | D30: 45697 | E30: =ISNUMBER(D30) -> TRUE | F30: 45697 | G30: Tennis Racket | H30: Sports | J30: 587.64 | L30: Credit Card | M30: Returned
A31: 194 | B31: Customer_194 | C31: ORD-69764 | D31: 45698 | E31: =ISNUMBER(D31) -> TRUE | F31: 45698 | G31: Lamp | H31: Home | I31: 5 | J31: 944.54 | L31: Cash on Delivery | M31: Returned | N31: 4722.7
A32: 117 | B32: Customer_117 | C32: ORD-72751 | D32: 45700 | E32: =ISNUMBER(D32) -> TRUE | F32: 45700 | G32: Blender | H32: electronic | I32: -2 | J32: 10000 | L32: Cash on Delivery | M32: Processing | N32: -20000
A33: 141 | B33: Customer_141 | C33: ORD-45059 | D33: 45701 | E33: =ISNUMBER(D33) -> TRUE | F33: 45701 | G33: Fiction | H33: Books | I33: 3 | J33: 546.04 | L33: Cash on Delivery | M33: Returned | N33: 1638.12
A34: 184 | B34: Customer_184 | C34: ORD-67799 | D34: 45703 | E34: =ISNUMBER(D34) -> TRUE | F34: 45703 | G34: Jeans | I34: 4 | J34: 101.19 | L34: Bank Transfer | M34: Processing | N34: 404.76
A35: 154 | B35: Customer_154 | C35: ORD-95990 | D35: 45709 | E35: =ISNUMBER(D35) -> TRUE | F35: 45709 | G35: Blender | H35: Home | I35: 5 | J35: 789.64 | L35: Cash on Delivery | M35: Cancelled | N35: 3948.2
A36: 137 | B36: Customer_137 | C36: ORD-91254 | D36: 45711 | E36: =ISNUMBER(D36) -> TRUE | F36: 45711 | G36: Vacuum | H36: Home | I36: 3 | J36: -100 | L36: Cash on Delivery | M36: Delivered | N36: -300
A37: 175 | B37: Customer_175 | C37: ORD-56651 | D37: 45712 | E37: =ISNUMBER(D37) -> TRUE | F37: 45712 | G37: Headphones | H37: Electronics | I37: 1 | J37: 111.36 | L37: Credit Card | M37: Processing | N37: 111.36
A38: 175 | B38: Customer_175 | C38: ORD-56651 | D38: 45712 | E38: =ISNUMBER(D38) -> TRUE | F38: 45712 | G38: Headphones | H38: Electronics | I38: 1 | J38: 111.36 | L38: Credit Card | M38: Processing | N38: 77.952
A39: 140 | B39: Customer_140 | C39: ORD-67096 | D39: 45714 | E39: =ISNUMBER(D39) -> TRUE | F39: 45714 | G39: Fiction | H39: Books | I39: 4 | J39: 588.98 | L39: Credit Card | M39: Returned | N39: 2355.92
A40: 112 | B40: Customer_112 | C40: ORD-80867 | D40: 45718 | E40: =ISNUMBER(D40) -> TRUE | F40: 45718 | G40: Shoes | H40: Clothing | I40: 4 | J40: 752.13 | L40: Bank Transfer | M40: Delivered | N40: 3008.52
A41: 183 | B41: Customer_183 | C41: ORD-20916 | D41: 45726 | E41: =ISNUMBER(D41) -> TRUE | F41: 45726 | G41: Shoes | H41: Clothing | I41: 5 | L41: Cash on Delivery | M41: Returned
A42: 148 | B42: Customer_148 | C42: ORD-38423 | D42: 45729 | E42: =ISNUMBER(D42) -> TRUE | F42: 45729 | G42: Tennis Racket | H42: Sports | I42: 1 | J42: 660.98 | L42: Cash on Delivery | M42: Returned | N42: 660.98
A43: 103 | B43: Customer_103 | C43: ORD-57811 | D43: 45735 | E43: =ISNUMBER(D43) -> TRUE | F43: 45735 | G43: Science | H43: Books | I43: 5 | J43: 233.92 | L43: PayPal | M43: Processing | N43: 1169.6
A44: 180 | B44: Customer_180 | C44: ORD-86629 | D44: 45742 | E44: =ISNUMBER(D44) -> TRUE | F44: 45742 | G44: Laptop | I44: 2 | J44: 418.38 | L44: Credit Card | M44: Processing | N44: 836.76
A45: 132 | B45: Customer_132 | C45: ORD-40186 | D45: 45749 | E45: =ISNUMBER(D45) -> TRUE | F45: 45749 | G45: Yoga Mat | H45: ELECTRONICS | I45: 1 | J45: 266.7 | L45: PayPal | M45: Delivered | N45: 266.7
A46: 158 | B46: Customer_158 | C46: ORD-35817 | D46: 45752 | E46: =ISNUMBER(D46) -> TRUE | F46: 45752 | G46: Smartwatch | H46: Electronics | I46: 1 | J46: 933.58 | L46: Cash on Delivery | M46: Shipped | N46: 933.58
A47: 147 | B47: Customer_147 | C47: ORD-80707 | D47: 45778 | E47: =ISNUMBER(D47) -> TRUE | F47: 45778 | G47: Jacket | H47: Clothing | I47: 4 | J47: 596.15 | L47: Cash on Delivery | M47: Shipped | N47: 2384.6
A48: 155 | B48: Customer_155 | C48: ORD-20182 | D48: 45778 | E48: =ISNUMBER(D48) -> TRUE | F48: 45778 | G48: shoes | H48: Clothing | I48: 1 | J48: 40.95 | L48: PayPal | M48: Returned | N48: 40.95
A49: 109 | B49: Customer_109 | C49: ORD-18512 | D49: 45780 | E49: =ISNUMBER(D49) -> TRUE | F49: 45780 | G49: Tennis Racket | H49: Sports | I49: 5 | J49: 168.34 | L49: Credit Card | M49: Shipped | N49: 841.7
A50: 127 | B50: Customer_127 | C50: ORD-65482 | D50: 45789 | E50: =ISNUMBER(D50) -> TRUE | F50: 45789 | G50: Blender | H50: Home | I50: 5 | J50: 336.02 | L50: Bank Transfer | M50: Returned | N50: 1680.1
A51: 122 | B51: Customer_122 | C51: ORD-21443 | D51: 45793 | E51: =ISNUMBER(D51) -> TRUE | F51: 45793 | G51: Microwave | H51: Home | I51: 2 | J51: 556.93 | L51: PayPal | M51: Shipped | N51: 1113.86
A52: 126 | B52: Customer_126 | C52: ORD-11261 | D52: 45795 | E52: =ISNUMBER(D52) -> TRUE | F52: 45795 | G52: Shoes | H52: Clothing | I52: 4 | J52: 836.8 | L52: Bank Transfer | M52: Cancelled | N52: 3347.2
A53: 162 | B53: Customer_162 | C53: ORD-27743 | D53: 45796 | E53: =ISNUMBER(D53) -> TRUE | F53: 45796 | G53: Blender | H53: Home | I53: 2 | J53: 155.76 | L53: Credit Card | M53: Returned | N53: 311.52
A54: 118 | B54: Customer_118 | C54: ORD-96061 | D54: 45808 | E54: =ISNUMBER(D54) -> TRUE | F54: 45808 | G54: Science | H54: Books | I54: 5 | J54: 247.82 | L54: PayPal | M54: Processing | N54: 1239.1
A55: 124 | B55: Customer_124 | C55: ORD-46136 | D55: 45808 | E55: =ISNUMBER(D55) -> TRUE | F55: 45808 | G55: Comics | H55: Books | I55: 5 | L55: PayPal | M55: Cancelled
A56: 193 | B56: Customer_193 | C56: ORD-42475 | D56: 45814 | E56: =ISNUMBER(D56) -> TRUE | F56: 45814 | G56: Basketball | J56: 522.02 | L56: PayPal | M56: Shipped
A57: 131 | B57: Customer_131 | C57: ORD-91396 | D57: 45819 | E57: =ISNUMBER(D57) -> TRUE | F57: 45819 | G57: Lamp | H57: Home | I57: 5 | J57: 616.63 | L57: PayPal | M57: Shipped | N57: 3083.15
A58: 136 | B58: Customer_136 | C58: ORD-20985 | D58: 45820 | E58: =ISNUMBER(D58) -> TRUE | F58: 45820 | G58: Headphones | I58: 1 | J58: 696.71 | L58: Credit Card | M58: Delivered | N58: 696.71
A59: 120 | B59: Customer_120 | C59: ORD-14659 | D59: 45821 | E59: =ISNUMBER(D59) -> TRUE | F59: 45821 | G59: Yoga Mat | H59: ELECTRONICS | I59: 5 | J59: 300 | L59: Credit Card | M59: Cancelled
A60: 195 | B60: Customer_195 | C60: ORD-82876 | D60: 45827 | E60: =ISNUMBER(D60) -> TRUE | F60: 45827 | G60: Biography | H60: Books | I60: 5 | J60: 817.46 | L60: Cash on Delivery | M60: Returned | N60: 4087.3
A61: 129 | B61: Customer_129 | C61: ORD-48863 | D61: 45830 | E61: =ISNUMBER(D61) -> TRUE | F61: 45830 | G61: Science | H61: Books | I61: 4 | J61: 736.71 | L61: Bank Transfer | M61: Returned | N61: 2946.84
A62: 197 | B62: Customer_197 | C62: ORD-79139 | D62: 45831 | E62: =ISNUMBER(D62) -> TRUE | F62: 45831 | G62: Blender | H62: Home | I62: 1 | J62: 160.16 | L62: PayPal | M62: Cancelled | N62: 160.16
A63: 149 | B63: Customer_149 | C63: ORD-95911 | D63: 45837 | E63: =ISNUMBER(D63) -> TRUE | F63: 45837 | G63: Comics | H63: Books | I63: 5 | J63: 896.38 | L63: Bank Transfer | M63: Cancelled | N63: 4481.9
A64: 190 | B64: Customer_190 | C64: ORD-38469 | D64: 45837 | E64: =ISNUMBER(D64) -> TRUE | F64: 45837 | G64: Vacuum | H64: Home | I64: 1 | J64: 920.37 | L64: Bank Transfer | M64: Processing | N64: 920.37
A65: 151 | B65: Customer_151 | C65: ORD-56552 | D65: 45839 | E65: =ISNUMBER(D65) -> TRUE | F65: 45839 | G65: Comics | H65: Books | I65: 2 | J65: 457.16 | L65: PayPal | M65: Processing | N65: 640.024
A66: 166 | B66: Customer_166 | C66: ORD-97756 | D66: 45841 | E66: =ISNUMBER(D66) -> TRUE | F66: 45841 | G66: T-shirt | H66: electronics | I66: 2 | J66: 569.38 | L66: Cash on Delivery | M66: Shipped | N66: 1138.76
A67: 101 | B67: Customer_101 | C67: ORD-35783 | D67: 45843 | E67: =ISNUMBER(D67) -> TRUE | F67: 45843 | G67: Smartphone | H67: Electronics | I67: 2 | J67: abd | L67: PayPal | M67: Processing
A68: 146 | B68: Customer_146 | C68: ORD-32755 | D68: 45847 | E68: =ISNUMBER(D68) -> TRUE | F68: 45847 | G68: Basketball | H68: electronic | I68: 2 | J68: 705.42 | L68: Bank Transfer | M68: Processing | N68: 1410.84
A69: 146 | B69: Customer_146 | C69: ORD-32755 | D69: 45847 | E69: =ISNUMBER(D69) -> TRUE | F69: 45847 | G69: Basketball | H69: electronic | I69: 2 | J69: 705.42 | L69: Bank Transfer | M69: Processing | N69: 1410.84
A70: 143 | B70: Customer_143 | C70: ORD-14329 | D70: 45849 | E70: =ISNUMBER(D70) -> TRUE | F70: 45849 | G70: T-shirt | H70: Clothing | I70: 5 | J70: 826.77 | L70: Bank Transfer | M70: Cancelled | N70: 4133.85
A71: 153 | B71: Customer_153 | C71: ORD-29721 | D71: 45854 | E71: =ISNUMBER(D71) -> TRUE | F71: 45854 | G71: Yoga Mat | H71: Sports | I71: 4 | J71: 278.9 | L71: Cash on Delivery | M71: Processing | N71: 1115.6
A72: 191 | B72: Customer_191 | C72: ORD-41810 | D72: 45856 | E72: =ISNUMBER(D72) -> TRUE | F72: 45856 | G72: Fiction | H72: Books | I72: 2 | J72: 881.02 | L72: Cash on Delivery | M72: Returned | N72: 1762.04
A73: 176 | B73: Customer_176 | C73: ORD-95794 | D73: 45860 | E73: =ISNUMBER(D73) -> TRUE | F73: 45860 | G73: Comics | H73: Books | I73: 5 | J73: 530.52 | L73: Cash on Delivery | M73: Shipped | N73: 2652.6
A74: 113 | B74: Customer_113 | C74: ORD-23994 | D74: 45862 | E74: =ISNUMBER(D74) -> TRUE | F74: 45862 | G74: Fiction | H74: Books | I74: 1 | J74: 411.81 | L74: Credit Card | M74: Processing | N74: 411.81
A75: 198 | B75: Customer_198 | C75: ORD-14608 | D75: 45865 | E75: =ISNUMBER(D75) -> TRUE | F75: 45865 | G75: Vacuum | I75: 2 | J75: 497.01 | L75: Cash on Delivery | M75: Shipped | N75: 994.02
A76: 159 | B76: Customer_159 | C76: ORD-98162 | D76: 45866 | E76: =ISNUMBER(D76) -> TRUE | F76: 45866 | G76: Microwave | H76: Home | I76: 3 | J76: 163.16 | L76: PayPal | M76: Shipped | N76: 489.48
A77: 177 | B77: Customer_177 | C77: ORD-64136 | D77: 45866 | E77: =ISNUMBER(D77) -> TRUE | F77: 45866 | G77: Laptop | H77: Electronics | I77: 1 | J77: 69.48 | L77: Bank Transfer | M77: Returned | N77: 69.48
A78: 182 | B78: Customer_182 | C78: ORD-79672 | D78: 45872 | E78: =ISNUMBER(D78) -> TRUE | F78: 45872 | G78: Shoes | I78: 4 | J78: 538.35 | L78: PayPal | M78: Processing | N78: 2153.4
A79: 167 | B79: Customer_167 | C79: ORD-30329 | D79: 45876 | E79: =ISNUMBER(D79) -> TRUE | F79: 45876 | G79: Basketball | H79: Sports | J79: 593.93 | L79: Cash on Delivery | M79: Processing
A80: 138 | B80: Customer_138 | C80: ORD-34319 | D80: 45878 | E80: =ISNUMBER(D80) -> TRUE | F80: 45878 | G80: Lamp | H80: Home | I80: 1 | J80: 531.06 | L80: PayPal | M80: Processing | N80: 531.06
A81: 169 | B81: Customer_169 | C81: ORD-75539 | D81: 45881 | E81: =ISNUMBER(D81) -> TRUE | F81: 45881 | G81: Basketball | H81: Sports | I81: 1 | J81: 582.13 | L81: Credit Card | M81: Returned | N81: 582.13
A82: 185 | B82: Customer_185 | C82: ORD-57123 | D82: 45883 | E82: =ISNUMBER(D82) -> TRUE | F82: 45883 | G82: Football | H82: Sports | I82: 2 | J82: 730.92 | L82: Cash on Delivery | M82: Cancelled | N82: 1023.288
A83: 189 | B83: Customer_189 | C83: ORD-30627 | D83: 45883 | E83: =ISNUMBER(D83) -> TRUE | F83: 45883 | G83: Lamp | H83: Home | I83: 1 | J83: 814.68 | L83: Cash on Delivery | M83: Returned | N83: 814.68
A84: 130 | B84: Customer_130 | C84: ORD-34007 | D84: 45884 | E84: =ISNUMBER(D84) -> TRUE | F84: 45884 | G84: Tennis Racket | H84: Sports | I84: 2 | L84: Bank Transfer | M84: Processing
A85: 179 | B85: Customer_179 | C85: ORD-99328 | D85: 45903 | E85: =ISNUMBER(D85) -> TRUE | F85: 45903 | G85: Yoga Mat | H85: Sports | I85: 3 | J85: 868.67 | L85: PayPal | M85: Delivered | N85: 2606.01
A86: 178 | B86: Customer_178 | C86: ORD-89906 | D86: 45918 | E86: =ISNUMBER(D86) -> TRUE | F86: 45918 | G86: Tennis Racket | H86: Sports | I86: 3 | J86: 472.14 | L86: PayPal | M86: Returned | N86: 1416.42
A87: 174 | B87: Customer_174 | C87: ORD-16766 | D87: 45920 | E87: =ISNUMBER(D87) -> TRUE | F87: 45920 | G87: Microwave | H87: ELECTRONICS | I87: 4 | J87: 187.48 | L87: Credit Card | M87: Returned | N87: 749.92
A88: 152 | B88: Customer_152 | C88: ORD-72869 | D88: 45922 | E88: =ISNUMBER(D88) -> TRUE | F88: 45922 | G88: Lamp | H88: Home | I88: 3 | J88: 233.11 | L88: PayPal | M88: Returned | N88: 699.33
A89: 110 | B89: Customer_110 | C89: ORD-61020 | D89: 45926 | E89: =ISNUMBER(D89) -> TRUE | F89: 45926 | G89: Basketball | H89: sports | I89: 5 | J89: 400 | L89: Cash on Delivery | M89: Cancelled | N89: =I89*J89 -> 2000
A90: 170 | B90: Customer_170 | C90: ORD-21530 | D90: 45933 | E90: =ISNUMBER(D90) -> TRUE | F90: 45933 | G90: Jeans | H90: Clothing | I90: 5 | J90: 741.63 | L90: Bank Transfer | M90: Processing | N90: 3708.15
A91: 134 | B91: Customer_134 | C91: ORD-16585 | D91: 45934 | E91: =ISNUMBER(D91) -> TRUE | F91: 45934 | G91: T-shirt | H91: Clothing | I91: 5 | J91: 591.53 | L91: PayPal | M91: Shipped | N91: -2957.65
A92: 123 | B92: Customer_123 | C92: ORD-11314 | D92: 45936 | E92: =ISNUMBER(D92) -> TRUE | F92: 45936 | G92: Vacuum | H92: electronic | I92: 3 | J92: 615.91 | L92: Cash on Delivery | M92: Cancelled | N92: 1847.73
A93: 186 | B93: Customer_186 | C93: ORD-90569 | D93: 45936 | E93: =ISNUMBER(D93) -> TRUE | F93: 45936 | G93: Laptop | H93: Electronics | I93: 1 | J93: 365.34 | L93: Bank Transfer | M93: Delivered | N93: 365.34
A94: 121 | B94: Customer_121 | C94: ORD-80067 | D94: 45941 | E94: =ISNUMBER(D94) -> TRUE | F94: 45941 | G94: Basketball | H94: Sports | I94: 4 | J94: 523.01 | L94: Credit Card | M94: Delivered | N94: 2092.04
A95: 173 | B95: Customer_173 | C95: ORD-42171 | D95: 45941 | E95: =ISNUMBER(D95) -> TRUE | F95: 45941 | G95: Lamp | H95: Home | I95: 5 | J95: 351.89 | L95: Credit Card | M95: Shipped | N95: 1759.45
A96: 104 | B96: Customer_104 | C96: ORD-93614 | D96: 45950 | E96: =ISNUMBER(D96) -> TRUE | F96: 45950 | G96: Biography | H96: Books | I96: 1 | J96: 552.51 | L96: Cash on Delivery | M96: Processing | N96: 552.51
A97: 111 | B97: Customer_111 | C97: ORD-72349 | D97: 45952 | E97: =ISNUMBER(D97) -> TRUE | F97: 45952 | G97: Comics | H97: Books | I97: 2 | J97: 865.77 | L97: Credit Card | M97: Returned | N97: 1731.54
A98: 108 | B98: Customer_108 | C98: ORD-64400 | D98: 45953 | E98: =ISNUMBER(D98) -> TRUE | F98: 45953 | G98: Science | H98: Books | I98: 1 | J98: 600.29 | L98: Cash on Delivery | M98: Processing | N98: 600.29
A99: 116 | B99: Customer_116 | C99: ORD-63660 | D99: 45960 | E99: =ISNUMBER(D99) -> TRUE | F99: 45960 | G99: Microwave | H99: Home | I99: 4 | L99: Cash on Delivery | M99: Processing
A100: 142 | B100: Customer_142 | C100: ORD-69018 | D100: 45960 | E100: =ISNUMBER(D100) -> TRUE | F100: 45960 | G100: Shoes | H100: Clothing | I100: 5 | J100: 645.26 | L100: Credit Card | M100: Shipped | N100: 2258.41
...
